Workbook

Sheet Resumo
A1: Produtos, preços e custos — Jacartta e Espaço de Bicho
A3: Shopee: 14/08/2026, 12:39:15 • custos Olist: 14/08/2026, 14:11:14 (horário de Brasília)
A5: Anúncios ativos | C5: Produtos/variações | E5: Em promoção | G5: Sem promoção
A6: 388 | C6: 700 | E6: 500 | G6: 200
A9: Resumo por loja
A10: Loja | B10: Anúncios | C10: Produtos/variações | D10: Em promoção | E10: Sem promoção | F10: % em promoção
A11: Espaço De Bicho | B11: 189 | C11: 286 | D11: 202 | E11: 84 | F11: 0.70629371
A12: Jacartta | B12: 199 | C12: 414 | D12: 298 | E12: 116 | F12: 0.71980676
A13: Total | B13: =SUBTOTAL(109,ResumoLojas[Anúncios]) | C13: =SUBTOTAL(109,ResumoLojas[Produtos/variações]) | D13: =SUBTOTAL(109,ResumoLojas[Em promoção]) | E13: =SUBTOTAL(109,ResumoLojas[Sem promoção]) | F13: =D13/C13
A15: Como interpretar os preços
A16: Preço final = preço promocional quando houver promoção ativa; caso contrário, preço de venda atual retornado pela Shopee.
A18: Fontes: Shopee Open Platform — https://partner.shopeemobile.com • Olist ERP/API — https://olist.com
A20: Cobertura dos custos Olist
A21: Loja | B21: Linhas | C21: Localizadas | D21: Custo > R$ 0 | E21: Custo R$ 0 | F21: Sem correspondência
A22: Espaço De Bicho | B22: 286 | C22: =COUNTIFS(Produtos!$A$5:$A$695,A22,Produtos!$O$5:$O$695,"<>") | D22: =COUNTIFS(Produtos!$A$5:$A$695,A22,Produtos!$O$5:$O$695,">0") | E22: =COUNTIFS(Produtos!$A$5:$A$695,A22,Produtos!$O$5:$O$695,"=0") | F22: =COUNTIFS(Produtos!$A$5:$A$695,A22,Produtos!$O$5:$O$695,"")
A23: Jacartta | B23: 414 | C23: =COUNTIFS(Produtos!$A$5:$A$695,A23,Produtos!$O$5:$O$695,"<>") | D23: =COUNTIFS(Produtos!$A$5:$A$695,A23,Produtos!$O$5:$O$695,">0") | E23: =COUNTIFS(Produtos!$A$5:$A$695,A23,Produtos!$O$5:$O$695,"=0") | F23: =COUNTIFS(Produtos!$A$5:$A$695,A23,Produtos!$O$5:$O$695,"")
A24: Total | B24: 700 | C24: =SUM(C22:C23) | D24: =SUM(D22:D23) | E24: =SUM(E22:E23) | F24: =SUM(F22:F23)
A26: Leitura: custo positivo = valor cadastrado; R$ 0,00 = produto localizado com custo zerado na Olist; vazio = sem correspondência exata segura.

Sheet Produtos
A1: Catálogo ativo com preços finais, promoções e custos Olist
A2: Uma linha por produto/variação. Custo Olist: R$ 0,00 = custo zerado no ERP; vazio = sem correspondência segura. | V2: Custo = preco_custo do cadastro Olist consultado hoje via API. QTD = unidades Olist por unidade do anúncio, derivada dos pedidos casados. | W2: Custo: anúncio de KIT usa o valor da aba de kits da Olist (componente × quantidade); produto unitário usa o preço de custo do cadastro. Conferido ao vivo em 16/08. Preços (I,K) do sync Shopee 16/08 ~13h50.
M3: ANÁLISE JULIANO | V3: PREENCHIDO PELO ORÁCULO — 16/08/2026 (custos conferidos AO VIVO na API da Olist)
A4: Loja | B4: Produto | C4: Variação | D4: SKU vendedor | E4: Item ID | F4: Variação ID | G4: Status | H4: Preço cadastrado | I4: Preço venda atual | J4: Em promoção? | K4: Preço promocional | L4: Preço final | M4: QTD | N4: Custo Unitário | O4: Custo Olist | P4: Lucro / Prejuizo | Q4: Desconto % | R4: ID(s) promoção | S4: Início promoção | T4: Fim promoção | U4: Categoria ID | V4: SKU Olist | W4: Origem do custo | X4: Pedidos casados | Y4: Checagem de modelo
A5: Espaço De Bicho | B5: 3 Rolos Removedor De Pelos Pet de Gato e Cachorro Removedor de pelos | C5: 2 UNIDADES | D5: 2-ROLO-REMOVEDOR | E5: 54964685255 | F5: 262815678259 | G5: NORMAL | H5: 89.9 | I5: 37.9 | J5: SIM | K5: 37.9 | L5: =IF(K5<>"",K5,I5) | O5: 28.65 | P5: =IF($O5="","",L5-O5-(L5*IF(L5<=79.99,20%,14%)+IF(L5<=79.99,4,IF(L5<=99.99,16,IF(L5<=199.99,20,IF(L5<=499.99,26,28)))))-L5*1.3%-L5*6%-(L5-O5)*9.25%-L5*3%-L5*3%-1) | Q5: =IF(AND(K5<>"",H5>0),(H5-K5)/H5,"") | R5: 909477973245952 | S5: 46144.383 | T5: 46295.438 | U5: 100929 | W5: custo preexistente (busca por texto) mantido
A6: Espaço De Bicho | B6: Adubo Fertilizante Mineral Forth Rosa Do Deserto 3kg/400g | C6: 3KG | D6: ADUBO-FORTH-ROSA-3KG | E6: 22593696013 | F6: 169406379212 | G6: NORMAL | H6: 79.9 | I6: 59.6 | J6: SIM | K6: 59.6 | L6: =IF(K6<>"",K6,I6) | M6: 1 | N6: 39.25 | O6: =ROUND(M6*N6,2) | P6: =IF($O6="","",L6-O6-(L6*IF(L6<=79.99,20%,14%)+IF(L6<=79.99,4,IF(L6<=99.99,16,IF(L6<=199.99,20,IF(L6<=499.99,26,28)))))-L6*1.3%-L6*6%-(L6-O6)*9.25%-L6*3%-L6*3%-1) | Q6: =IF(AND(K6<>"",H6>0),(H6-K6)/H6,"") | R6: 909477973245952 | S6: 46144.383 | T6: 46295.438 | U6: 101179 | V6: 213560 | W6: venda casada (10 pedidos) | X6: 10 | Y6: ok
A7: Espaço De Bicho | B7: Anti-Inflamatório Alcort Para Cachorros Com 10 Comprimidos De 5mg | C7: 5mg | D7: ALCORT-5MG-10COMP | E7: 22799241855 | F7: 109871690918 | G7: NORMAL | H7: 99.9 | I7: 99.9 | J7: NÃO | L7: =IF(K7<>"",K7,I7) | P7: =IF($O7="","",L7-O7-(L7*IF(L7<=79.99,20%,14%)+IF(L7<=79.99,4,IF(L7<=99.99,16,IF(L7<=199.99,20,IF(L7<=499.99,26,28)))))-L7*1.3%-L7*6%-(L7-O7)*9.25%-L7*3%-L7*3%-1) | Q7: =IF(AND(K7<>"",H7>0),(H7-K7)/H7,"") | U7: 100942 | V7: ALCORT-5MG-10COMP | W7: SKU idêntico na Olist · CUSTO ZERADO na Olist (conferido hoje) | Y7: ok
A8: Espaço De Bicho | B8: Antipulgas E Carrapatos Frontline Top Spot Gato 1 A 10kg | C8: Sem variação | D8: 0667 | E8: 20959149444 | F8: 0 | G8: NORMAL | H8: 38.9 | I8: 38.9 | J8: NÃO | L8: =IF(K8<>"",K8,I8) | P8: =IF($O8="","",L8-O8-(L8*IF(L8<=79.99,20%,14%)+IF(L8<=79.99,4,IF(L8<=99.99,16,IF(L8<=199.99,20,IF(L8<=499.99,26,28)))))-L8*1.3%-L8*6%-(L8-O8)*9.25%-L8*3%-L8*3%-1) | Q8: =IF(AND(K8<>"",H8>0),(H8-K8)/H8,"") | U8: 100942 | V8: 0667 | W8: SKU idêntico na Olist · CUSTO ZERADO na Olist (conferido hoje) | Y8: ok
A9: Espaço De Bicho | B9: Antipulgas Invicto Cães 11,4 Kg A 57kg 1 Comprimido | C9: Sem variação | D9: 010 | E9: 21169839582 | F9: 0 | G9: NORMAL | H9: 17.9 | I9: 17.9 | J9: NÃO | L9: =IF(K9<>"",K9,I9) | M9: 1 | N9: 6.52 | O9: =ROUND(M9*N9,2) | P9: =IF($O9="","",L9-O9-(L9*IF(L9<=79.99,20%,14%)+IF(L9<=79.99,4,IF(L9<=99.99,16,IF(L9<=199.99,20,IF(L9<=499.99,26,28)))))-L9*1.3%-L9*6%-(L9-O9)*9.25%-L9*3%-L9*3%-1) | Q9: =IF(AND(K9<>"",H9>0),(H9-K9)/H9,"") | U9: 100942 | V9: 213547 | W9: SKU do de-para · custo do KIT 213690 (1× 213547) | X9: 2 | Y9: ok
A10: Espaço De Bicho | B10: Antitóxico Duprat Oral 20ML Cães Gatos | C10: Sem variação | D10: ANTITOXICO-DUPRAT-ORAL-20 ML | E10: 22199050344 | F10: 0 | G10: NORMAL | H10: 59.9 | I10: 18.83 | J10: SIM | K10: 18.83 | L10: =IF(K10<>"",K10,I10) | P10: =IF($O10="","",L10-O10-(L10*IF(L10<=79.99,20%,14%)+IF(L10<=79.99,4,IF(L10<=99.99,16,IF(L10<=199.99,20,IF(L10<=499.99,26,28)))))-L10*1.3%-L10*6%-(L10-O10)*9.25%-L10*3%-L10*3%-1) | Q10: =IF(AND(K10<>"",H10>0),(H10-K10)/H10,"") | R10: 909477973245952 | S10: 46144.383 | T10: 46295.438 | U10: 100942 | V10: ANTITOXICO-DUPRAT-ORAL-20 ML | W10: SKU idêntico na Olist · CUSTO ZERADO na Olist (conferido hoje) | Y10: ok
A11: Espaço De Bicho | B11: Tapete Higienico Good Pad 50 Unidades Envio Imediato | C11: Sem variação | D11: 0771 | E11: 17981944804 | F11: 0 | G11: NORMAL | H11: 99.9 | I11: 44.9 | J11: SIM | K11: 44.9 | L11: =IF(K11<>"",K11,I11) | M11: 1 | N11: 33.46 | O11: =ROUND(M11*N11,2) | P11: =IF($O11="","",L11-O11-(L11*IF(L11<=79.99,20%,14%)+IF(L11<=79.99,4,IF(L11<=99.99,16,IF(L11<=199.99,20,IF(L11<=499.99,26,28)))))-L11*1.3%-L11*6%-(L11-O11)*9.25%-L11*3%-L11*3%-1) | Q11: =IF(AND(K11<>"",H11>0),(H11-K11)/H11,"") | R11: 909477973245952 | S11: 46144.383 | T11: 46295.438 | U11: 100926 | V11: 212961 | W11: venda casada (1160 pedidos) · custo do KIT 213830 (1× 212961) | X11: 1160 | Y11: ok
A12: Espaço De Bicho | B12: Bebedouro Beija Flor Luxo com chapéu e poleiro - Jelplast Sortido | C12: Sem variação | D12: 64 | E12: 18499198968 | F12: 0 | G12: NORMAL | H12: 29.9 | I12: 13.9 | J12: SIM | K12: 13.9 | L12: =IF(K12<>"",K12,I12) | P12: =IF($O12="","",L12-O12-(L12*IF(L12<=79.99,20%,14%)+IF(L12<=79.99,4,IF(L12<=99.99,16,IF(L12<=199.99,20,IF(L12<=499.99,26,28)))))-L12*1.3%-L12*6%-(L12-O12)*9.25%-L12*3%-L12*3%-1) | Q12: =IF(AND(K12<>"",H12>0),(H12-K12)/H12,"") | R12: 909477973245952 | S12: 46144.383 | T12: 46295.438 | U12: 100916 | V12: 64 | W12: SKU idêntico na Olist · CUSTO ZERADO na Olist (conferido hoje) | Y12: ok
A13: Espaço De Bicho | B13: Bolinha Com Guizo Brinquedo Para Gato Colorido | C13: Sem variação | D13: BOLA-GUIZO-CAT | E13: 22993543152 | F13: 0 | G13: NORMAL | H13: 19.9 | I13: 9.9 | J13: SIM | K13: 9.9 | L13: =IF(K13<>"",K13,I13) | M13: 1 | N13: 0.2 | O13: =ROUND(M13*N13,2) | P13: =IF($O13="","",L13-O13-(L13*IF(L13<=79.99,20%,14%)+IF(L13<=79.99,4,IF(L13<=99.99,16,IF(L13<=199.99,20,IF(L13<=499.99,26,28)))))-L13*1.3%-L13*6%-(L13-O13)*9.25%-L13*3%-L13*3%-1) | Q13: =IF(AND(K13<>"",H13>0),(H13-K13)/H13,"") | R13: 909477973245952 | S13: 46144.383 | T13: 46295.438 | U13: 101926 | V13: 212992 | W13: venda casada (25 pedidos) | X13: 25 | Y13: ok
A14: Espaço De Bicho | B14: Brinquedo Interativo P/ Gatos Varinha Arranhador Pena Ratinho | C14: PENA | D14: BRINQUEDO-PENA | E14: 19197811676 | F14: 229409372832 | G14: NORMAL | H14: 59.9 | I14: 19.89 | J14: SIM | K14: 19.89 | L14: =IF(K14<>"",K14,I14) | M14: 1 | N14: 12.2 | O14: =ROUND(M14*N14,2) | P14: =IF($O14="","",L14-O14-(L14*IF(L14<=79.99,20%,14%)+IF(L14<=79.99,4,IF(L14<=99.99,16,IF(L14<=199.99,20,IF(L14<=499.99,26,28)))))-L14*1.3%-L14*6%-(L14-O14)*9.25%-L14*3%-L14*3%-1) | Q14: =IF(AND(K14<>"",H14>0),(H14-K14)/H14,"") | R14: 909477973245952 | S14: 46144.383 | T14: 46295.438 | U14: 101678 | V14: 213556 | W14: venda casada (3 pedidos) | X14: 3 | Y14: ok
A15: Espaço De Bicho | B15: Brinquedo Interativo P/ Gatos Varinha Arranhador Pena Ratinho | C15: RATO | D15: BRINQUEDO-RATO | E15: 19197811676 | F15: 229409372831 | G15: NORMAL | H15: 59.9 | I15: 19.89 | J15: SIM | K15: 19.89 | L15: =IF(K15<>"",K15,I15) | M15: 1 | N15: 12.2 | O15: =ROUND(M15*N15,2) | P15: =IF($O15="","",L15-O15-(L15*IF(L15<=79.99,20%,14%)+IF(L15<=79.99,4,IF(L15<=99.99,16,IF(L15<=199.99,20,IF(L15<=499.99,26,28)))))-L15*1.3%-L15*6%-(L15-O15)*9.25%-L15*3%-L15*3%-1) | Q15: =IF(AND(K15<>"",H15>0),(H15-K15)/H15,"") | R15: 909477973245952 | S15: 46144.383 | T15: 46295.438 | U15: 101678 | V15: 213555 | W15: venda casada (7 pedidos) | X15: 7 | Y15: ok
A16: Espaço De Bicho | B16: Brinquedo Interativo Simulador de Pássaro- Varinha para provocar e estimular gato | C16: Sem variação | D16: BRINQUEDO-VARA-CAT | E16: 20699202925 | F16: 0 | G16: NORMAL | H16: 29.9 | I16: 25.9 | J16: SIM | K16: 25.9 | L16: =IF(K16<>"",K16,I16) | P16: =IF($O16="","",L16-O16-(L16*IF(L16<=79.99,20%,14%)+IF(L16<=79.99,4,IF(L16<=99.99,16,IF(L16<=199.99,20,IF(L16<=499.99,26,28)))))-L16*1.3%-L16*6%-(L16-O16)*9.25%-L16*3%-L16*3%-1) | Q16: =IF(AND(K16<>"",H16>0),(H16-K16)/H16,"") | R16: 909477973245952 | S16: 46144.383 | T16: 46295.438 | U16: 101925 | W16: ambíguo: 213575 (50%) vs BRINQUEDO-VARA-CAT | X16: 2
A17: Espaço De Bicho | B17: Brinquedo Mordedor Osso Bamboo Sabor Bacon Limpeza Dentes Tartaro Truqys | C17: Osso Pequeno | D17: 0332 | E17: 22196102653 | F17: 159766308983 | G17: NORMAL | H17: 44.9 | I17: 19.9 | J17: SIM | K17: 19.9 | L17: =IF(K17<>"",K17,I17) | M17: 1 | N17: 9.93 | O17: =ROUND(M17*N17,2) | P17: =IF($O17="","",L17-O17-(L17*IF(L17<=79.99,20%,14%)+IF(L17<=79.99,4,IF(L17<=99.99,16,IF(L17<=199.99,20,IF(L17<=499.99,26,28)))))-L17*1.3%-L17*6%-(L17-O17)*9.25%-L17*3%-L17*3%-1) | Q17: =IF(AND(K17<>"",H17>0),(H17-K17)/H17,"") | R17: 909477973245952 | S17: 46144.383 | T17: 46295.438 | U17: 101926 | V17: 215138 | W17: venda casada (1 pedido) | X17: 1 | Y17: ⚠ evidência fraca (1 pedido)
A18: Espaço De Bicho | B18: Brinquedo Varinha Gato Penas Pássaro Com Ventosa Fixa No Chão | C18: PRETO | D18: BRINQUEDO-VARA-CAT-PRETO | E18: 19997807516 | F18: 169399702997 | G18: NORMAL | H18: 39.9 | I18: 24.89 | J18: SIM | K18: 24.89 | L18: =IF(K18<>"",K18,I18) | M18: 1 | N18: 4.33 | O18: =ROUND(M18*N18,2) | P18: =IF($O18="","",L18-O18-(L18*IF(L18<=79.99,20%,14%)+IF(L18<=79.99,4,IF(L18<=99.99,16,IF(L18<=199.99,20,IF(L18<=499.99,26,28)))))-L18*1.3%-L18*6%-(L18-O18)*9.25%-L18*3%-L18*3%-1) | Q18: =IF(AND(K18<>"",H18>0),(H18-K18)/H18,"") | R18: 909477973245952 | S18: 46144.383 | T18: 46295.438 | U18: 101925 | V18: 213527 | W18: venda casada (13 pedidos) | X18: 13 | Y18: ok
A19: Espaço De Bicho | B19: Brinquedo Varinha Gato Penas Pássaro Com Ventosa Fixa No Chão | C19: ROSA | D19: BRINQUEDO-VARA-CAT-ROSA | E19: 19997807516 | F19: 169399702996 | G19: NORMAL | H19: 39.9 | I19: 19.9 | J19: SIM | K19: 19.9 | L19: =IF(K19<>"",K19,I19) | M19: 1 | N19: 4.33 | O19: =ROUND(M19*N19,2) | P19: =IF($O19="","",L19-O19-(L19*IF(L19<=79.99,20%,14%)+IF(L19<=79.99,4,IF(L19<=99.99,16,IF(L19<=199.99,20,IF(L19<=499.99,26,28)))))-L19*1.3%-L19*6%-(L19-O19)*9.25%-L19*3%-L19*3%-1) | Q19: =IF(AND(K19<>"",H19>0),(H19-K19)/H19,"") | R19: 909477973245952 | S19: 46144.383 | T19: 46295.438 | U19: 101925 | V19: 213528 | W19: venda casada (57 pedidos) | X19: 57 | Y19: ok
A20: Espaço De Bicho | B20: Cata caca passeio dos pet | C20: Sem variação | D20: 290 | E20: 21499666045 | F20: 0 | G20: NORMAL | H20: 29.9 | I20: 29.9 | J20: NÃO | L20: =IF(K20<>"",K20,I20) | P20: =IF($O20="","",L20-O20-(L20*IF(L20<=79.99,20%,14%)+IF(L20<=79.99,4,IF(L20<=99.99,16,IF(L20<=199.99,20,IF(L20<=499.99,26,28)))))-L20*1.3%-L20*6%-(L20-O20)*9.25%-L20*3%-L20*3%-1) | Q20: =IF(AND(K20<>"",H20>0),(H20-K20)/H20,"") | U20: 100927 | V20: 290 | W20: SKU idêntico na Olist · CUSTO ZERADO na Olist (conferido hoje) | Y20: ok
A21: Espaço De Bicho | B21: Duotrill 150mg 10 Comprimidos Para Cães E Gatos - Duprat | C21: Sem variação | D21: DUOTRILL-150MG-10COMP | E21: 23099049174 | F21: 0 | G21: NORMAL | H21: 99.9 | I21: 56.9 | J21: SIM | K21: 56.9 | L21: =IF(K21<>"",K21,I21) | P21: =IF($O21="","",L21-O21-(L21*IF(L21<=79.99,20%,14%)+IF(L21<=79.99,4,IF(L21<=99.99,16,IF(L21<=199.99,20,IF(L21<=499.99,26,28)))))-L21*1.3%-L21*6%-(L21-O21)*9.25%-L21*3%-L21*3%-1) | Q21: =IF(AND(K21<>"",H21>0),(H21-K21)/H21,"") | R21: 909477973245952 | S21: 46144.383 | T21: 46295.438 | U21: 100944 | V21: DUOTRILL-150MG-10COMP | W21: SKU idêntico na Olist · CUSTO ZERADO na Olist (conferido hoje) | Y21: ok
A22: Espaço De Bicho | B22: Duotrill 50 MG Duprat Blister C/ 10 Comprimidos Cães e Gatos | C22: Sem variação | D22: DUOTRILL-50MG-10-COMP | E22: 22899048121 | F22: 0 | G22: NORMAL | H22: 59.9 | I22: 17.99 | J22: SIM | K22: 17.99 | L22: =IF(K22<>"",K22,I22) | M22: 1 | N22: 8 | O22: =ROUND(M22*N22,2) | P22: =IF($O22="","",L22-O22-(L22*IF(L22<=79.99,20%,14%)+IF(L22<=79.99,4,IF(L22<=99.99,16,IF(L22<=199.99,20,IF(L22<=499.99,26,28)))))-L22*1.3%-L22*6%-(L22-O22)*9.25%-L22*3%-L22*3%-1) | Q22: =IF(AND(K22<>"",H22>0),(H22-K22)/H22,"") | R22: 909477973245952 | S22: 46144.383 | T22: 46295.438 | U22: 100942 | V22: 213398 | W22: venda casada (7 pedidos) | X22: 7 | Y22: ok
A23: Espaço De Bicho | B23: Duprantel Vermífugo Cães e Gatos- 4 Comprimidos - Duprat | C23: Sem variação | D23: DUPRANTEL-660MG-4COMPS | E23: 22999049495 | F23: 0 | G23: NORMAL | H23: 59.9 | I23: 14.9 | J23: SIM | K23: 14.9 | L23: =IF(K23<>"",K23,I23) | M23: 1 | N23: 17.46 | O23: =ROUND(M23*N23,2) | P23: =IF($O23="","",L23-O23-(L23*IF(L23<=79.99,20%,14%)+IF(L23<=79.99,4,IF(L23<=99.99,16,IF(L23<=199.99,20,IF(L23<=499.99,26,28)))))-L23*1.3%-L23*6%-(L23-O23)*9.25%-L23*3%-L23*3%-1) | Q23: =IF(AND(K23<>"",H23>0),(H23-K23)/H23,"") | R23: 909477973245952 | S23: 46144.383 | T23: 46295.438 | U23: 100942 | V23: 212433 | W23: venda casada (3 pedidos) | X23: 3 | Y23: ok
A24: Espaço De Bicho | B24: Duprazol Soluçao Oral 30 ML Anti-Helmíntico Cães e Gatos | C24: Sem variação | D24: DUPRAZOL-ORAL-30 ML | E24: 20599908178 | F24: 0 | G24: NORMAL | H24: 59.9 | I24: 17.9 | J24: SIM | K24: 17.9 | L24: =IF(K24<>"",K24,I24) | M24: 1 | N24: 9.4 | O24: =ROUND(M24*N24,2) | P24: =IF($O24="","",L24-O24-(L24*IF(L24<=79.99,20%,14%)+IF(L24<=79.99,4,IF(L24<=99.99,16,IF(L24<=199.99,20,IF(L24<=499.99,26,28)))))-L24*1.3%-L24*6%-(L24-O24)*9.25%-L24*3%-L24*3%-1) | Q24: =IF(AND(K24<>"",H24>0),(H24-K24)/H24,"") | R24: 909477973245952 | S24: 46144.383 | T24: 46295.438 | U24: 100942 | V24: 213480 | W24: venda casada (2 pedidos) | X24: 2 | Y24: ok
A25: Espaço De Bicho | B25: Gaiola Hamster Tubo 3 Andares Espaco De Bicho Completa com Rodinha | C25: AZUL | D25: GAIOLA-HAMSTER-PEQ-AZ | E25: 22098124819 | F25: 239414033397 | G25: NORMAL | H25: 199.9 | I25: 128.99 | J25: SIM | K25: 128.99 | L25: =IF(K25<>"",K25,I25) | M25: 1 | N25: 71.14 | O25: =ROUND(M25*N25,2) | P25: =IF($O25="","",L25-O25-(L25*IF(L25<=79.99,20%,14%)+IF(L25<=79.99,4,IF(L25<=99.99,16,IF(L25<=199.99,20,IF(L25<=499.99,26,28)))))-L25*1.3%-L25*6%-(L25-O25)*9.25%-L25*3%-L25*3%-1) | Q25: =IF(AND(K25<>"",H25>0),(H25-K25)/H25,"") | R25: 909477973245952 | S25: 46144.383 | T25: 46295.438 | U25: 101684 | V25: 213625 | W25: venda casada (1 pedido) | X25: 1 | Y25: ⚠ evidência fraca (1 pedido)
A26: Espaço De Bicho | B26: Gaiola Hamster Tubo 3 Andares Espaco De Bicho Completa com Rodinha | C26: ROXO | D26: GAIOLA-HAMSTER-PEQ-RX | E26: 22098124819 | F26: 239414033395 | G26: NORMAL | H26: 199.9 | I26: 149.89 | J26: SIM | K26: 149.89 | L26: =IF(K26<>"",K26,I26) | M26: 1 | N26: 71.14 | O26: =ROUND(M26*N26,2) | P26: =IF($O26="","",L26-O26-(L26*IF(L26<=79.99,20%,14%)+IF(L26<=79.99,4,IF(L26<=99.99,16,IF(L26<=199.99,20,IF(L26<=499.99,26,28)))))-L26*1.3%-L26*6%-(L26-O26)*9.25%-L26*3%-L26*3%-1) | Q26: =IF(AND(K26<>"",H26>0),(H26-K26)/H26,"") | R26: 909477973245952 | S26: 46144.383 | T26: 46295.438 | U26: 101684 | V26: 213625 | W26: herdado do anúncio | Y26: ok
A27: Espaço De Bicho | B27: Gaiola Hamster Tubo 3 Andares Espaco De Bicho Completa com Rodinha | C27: VERMELHO | D27: GAIOLA-HAMSTER-PEQ-VM | E27: 22098124819 | F27: 239414033396 | G27: NORMAL | H27: 199.9 | I27: 149.9 | J27: SIM | K27: 149.9 | L27: =IF(K27<>"",K27,I27) | M27: 1 | N27: 71.14 | O27: =ROUND(M27*N27,2) | P27: =IF($O27="","",L27-O27-(L27*IF(L27<=79.99,20%,14%)+IF(L27<=79.99,4,IF(L27<=99.99,16,IF(L27<=199.99,20,IF(L27<=499.99,26,28)))))-L27*1.3%-L27*6%-(L27-O27)*9.25%-L27*3%-L27*3%-1) | Q27: =IF(AND(K27<>"",H27>0),(H27-K27)/H27,"") | R27: 909477973245952 | S27: 46144.383 | T27: 46295.438 | U27: 101684 | V27: 213625 | W27: herdado do anúncio | Y27: ok
A28: Espaço De Bicho | B28: Glicosol Pet 50ml - Lavizoo Suplemento Cães E Gatos | C28: Sem variação | D28: GLICOSOL-50ML | E28: 21199252289 | F28: 0 | G28: NORMAL | H28: 59.9 | I28: 24.9 | J28: SIM | K28: 24.9 | L28: =IF(K28<>"",K28,I28) | P28: =IF($O28="","",L28-O28-(L28*IF(L28<=79.99,20%,14%)+IF(L28<=79.99,4,IF(L28<=99.99,16,IF(L28<=199.99,20,IF(L28<=499.99,26,28)))))-L28*1.3%-L28*6%-(L28-O28)*9.25%-L28*3%-L28*3%-1) | Q28: =IF(AND(K28<>"",H28>0),(H28-K28)/H28,"") | R28: 909477973245952 | S28: 46144.383 | T28: 46295.438 | U28: 100944 | V28: GLICOSOL-50ML | W28: SKU idêntico na Olist · CUSTO ZERADO na Olist (conferido hoje) | Y28: ok
A29: Espaço De Bicho | B29: Granulado De Madeira Higiênico para Gatos Absorve 5x Mais | C29: 10kg | D29: GRANULADO-GATO-10KG | E29: 23297634808 | F29: 179398139975 | G29: NORMAL | H29: 68.9 | I29: 42.9 | J29: SIM | K29: 42.9 | L29: =IF(K29<>"",K29,I29) | M29: 1 | N29: 14.54 | O29: =ROUND(M29*N29,2) | P29: =IF($O29="","",L29-O29-(L29*IF(L29<=79.99,20%,14%)+IF(L29<=79.99,4,IF(L29<=99.99,16,IF(L29<=199.99,20,IF(L29<=499.99,26,28)))))-L29*1.3%-L29*6%-(L29-O29)*9.25%-L29*3%-L29*3%-1) | Q29: =IF(AND(K29<>"",H29>0),(H29-K29)/H29,"") | R29: 909477973245952 | S29: 46144.383 | T29: 46295.438 | U29: 100923 | V29: 213515 | W29: venda casada (51 pedidos) | X29: 51 | Y29: ok
A30: Espaço De Bicho | B30: Granulado De Madeira Higiênico para Gatos Absorve 5x Mais | C30: 20kg | D30: GRANULADO-GATO-20KG | E30: 23297634808 | F30: 169709589663 | G30: NORMAL | H30: 99.9 | I30: 79.89 | J30: SIM | K30: 79.89 | L30: =IF(K30<>"",K30,I30) | M30: 1 | N30: 27.45 | O30: =ROUND(M30*N30,2) | P30: =IF($O30="","",L30-O30-(L30*IF(L30<=79.99,20%,14%)+IF(L30<=79.99,4,IF(L30<=99.99,16,IF(L30<=199.99,20,IF(L30<=499.99,26,28)))))-L30*1.3%-L30*6%-(L30-O30)*9.25%-L30*3%-L30*3%-1) | Q30: =IF(AND(K30<>"",H30>0),(H30-K30)/H30,"") | R30: 909477973245952 | S30: 46144.383 | T30: 46295.438 | U30: 100923 | V30: 213516 | W30: venda casada (36 pedidos) | X30: 36 | Y30: ok
A31: Espaço De Bicho | B31: Granulado De Madeira Higiênico para Gatos Absorve 5x Mais | C31: 2kg | D31: GRANULADO-GATO-2KG | E31: 23297634808 | F31: 179398139973 | G31: NORMAL | H31: 20.9 | I31: 14.9 | J31: NÃO | L31: =IF(K31<>"",K31,I31) | M31: 1 | N31: 2.35 | O31: =ROUND(M31*N31,2) | P31: =IF($O31="","",L31-O31-(L31*IF(L31<=79.99,20%,14%)+IF(L31<=79.99,4,IF(L31<=99.99,16,IF(L31<=199.99,20,IF(L31<=499.99,26,28)))))-L31*1.3%-L31*6%-(L31-O31)*9.25%-L31*3%-L31*3%-1) | Q31: =IF(AND(K31<>"",H31>0),(H31-K31)/H31,"") | U31: 100923 | V31: 213513 | W31: venda casada (9 pedidos) | X31: 9 | Y31: ok
A32: Espaço De Bicho | B32: Granulado De Madeira Higiênico para Gatos Absorve 5x Mais | C32: 4kg | D32: GRANULADO-GATO-4KG | E32: 23297634808 | F32: 179398139974 | G32: NORMAL | H32: 29.9 | I32: 29.59 | J32: SIM | K32: 29.59 | L32: =IF(K32<>"",K32,I32) | M32: 1 | N32: 2.35 | O32: =ROUND(M32*N32,2) | P32: =IF($O32="","",L32-O32-(L32*IF(L32<=79.99,20%,14%)+IF(L32<=79.99,4,IF(L32<=99.99,16,IF(L32<=199.99,20,IF(L32<=499.99,26,28)))))-L32*1.3%-L32*6%-(L32-O32)*9.25%-L32*3%-L32*3%-1) | Q32: =IF(AND(K32<>"",H32>0),(H32-K32)/H32,"") | R32: 909477973245952 | S32: 46144.383 | T32: 46295.438 | U32: 100923 | V32: 213514 | W32: venda casada (17 pedidos) | X32: 17 | Y32: ok
A33: Espaço De Bicho | B33: Invicto 11,4 Mg 6 Comprimidos (antipulgas Até 11,4kg) | C33: Sem variação | D33: 0023 | E33: 22914482891 | F33: 0 | G33: NORMAL | H33: 62.9 | I33: 59.9 | J33: SIM | K33: 59.9 | L33: =IF(K33<>"",K33,I33) | P33: =IF($O33="","",L33-O33-(L33*IF(L33<=79.99,20%,14%)+IF(L33<=79.99,4,IF(L33<=99.99,16,IF(L33<=199.99,20,IF(L33<=499.99,26,28)))))-L33*1.3%-L33*6%-(L33-O33)*9.25%-L33*3%-L33*3%-1) | Q33: =IF(AND(K33<>"",H33>0),(H33-K33)/H33,"") | R33: 909477973245952 | S33: 46144.383 | T33: 46295.438 | U33: 100942 | V33: 0023 | W33: SKU idêntico na Olist · CUSTO ZERADO na Olist (conferido hoje) | Y33: ok
A34: Espaço De Bicho | B34: Invicto 11,4 Mg Cão/gato Antipulga 20 Blister 1 Cp | C34: Sem variação | D34: 0644 | E34: 22914542066 | F34: 0 | G34: NORMAL | H34: 252.9 | I34: 252.9 | J34: NÃO | L34: =IF(K34<>"",K34,I34) | P34: =IF($O34="","",L34-O34-(L34*IF(L34<=79.99,20%,14%)+IF(L34<=79.99,4,IF(L34<=99.99,16,IF(L34<=199.99,20,IF(L34<=499.99,26,28)))))-L34*1.3%-L34*6%-(L34-O34)*9.25%-L34*3%-L34*3%-1) | Q34: =IF(AND(K34<>"",H34>0),(H34-K34)/H34,"") | U34: 100942 | V34: 0644 | W34: SKU idêntico na Olist · CUSTO ZERADO na Olist (conferido hoje) | Y34: ok
A35: Espaço De Bicho | B35: Invicto 57mg Antipulgas P/cães E Gatos De 11,4kg A 57kg - 1 Comprimido | C35: Sem variação | E35: 21997503469 | F35: 0 | G35: NORMAL | H35: 29.9 | I35: 16.9 | J35: SIM | K35: 16.9 | L35: =IF(K35<>"",K35,I35) | P35: =IF($O35="","",L35-O35-(L35*IF(L35<=79.99,20%,14%)+IF(L35<=79.99,4,IF(L35<=99.99,16,IF(L35<=199.99,20,IF(L35<=499.99,26,28)))))-L35*1.3%-L35*6%-(L35-O35)*9.25%-L35*3%-L35*3%-1) | Q35: =IF(AND(K35<>"",H35>0),(H35-K35)/H35,"") | R35: 909477973245952 | S35: 46144.383 | T35: 46295.438 | U35: 100942 | W35: sem correspondência
A36: Jacartta | B36: Tapete Higienico Good Pad 50 Unidades Envio Imediato | C36: Sem variação | D36: 0771 | E36: 17463955532 | F36: 0 | G36: NORMAL | H36: 64.9 | I36: 59.9 | J36: NÃO | L36: =IF(K36<>"",K36,I36) | M36: 1 | N36: 33.46 | O36: =ROUND(M36*N36,2) | P36: =IF($O36="","",L36-O36-(L36*IF(L36<=79.99,20%,14%)+IF(L36<=79.99,4,IF(L36<=99.99,16,IF(L36<=199.99,20,IF(L36<=499.99,26,28)))))-L36*1.3%-L36*6%-(L36-O36)*9.25%-L36*3%-L36*3%-1) | Q36: =IF(AND(K36<>"",H36>0),(H36-K36)/H36,"") | U36: 100926 | V36: 212961 | W36: venda casada (750 pedidos) · custo do KIT 213830 (1× 212961) | X36: 750 | Y36: ok
A37: Espaço De Bicho | B37: Kit 2 Bebedouro Para Beija Flor Aves Passaro Poleiro 250ml | C37: Kit 2 | D37: KIT-2-BEBEDOURO-BEIJAFLOR | E37: 23697343948 | F37: 219174198287 | G37: NORMAL | H37: 59.9 | I37: 19.9 | J37: SIM | K37: 19.9 | L37: =IF(K37<>"",K37,I37) | M37: 2 | N37: 3.35 | O37: =ROUND(M37*N37,2) | P37: =IF($O37="","",L37-O37-(L37*IF(L37<=79.99,20%,14%)+IF(L37<=79.99,4,IF(L37<=99.99,16,IF(L37<=199.99,20,IF(L37<=499.99,26,28)))))-L37*1.3%-L37*6%-(L37-O37)*9.25%-L37*3%-L37*3%-1) | Q37: =IF(AND(K37<>"",H37>0),(H37-K37)/H37,"") | R37: 909477973245952 | S37: 46144.383 | T37: 46295.438 | U37: 100916 | V37: 212811 | W37: venda casada (374 pedidos) · custo do KIT 213561 (2× 212811) | X37: 374 | Y37: ok
A38: Espaço De Bicho | B38: Kit 4 Areia Higiênica Biodegradável Grãos Finos Milho e Mandioca (100% Natural) - Espaço De Bicho | C38: Grãos Finos | D38: KIT4-AREIA-EDB-4KG-GF | E38: 58254481683 | F38: 229437018332 | G38: NORMAL | H38: 199.9 | I38: 199.9 | J38: NÃO | L38: =IF(K38<>"",K38,I38) | P38: =IF($O38="","",L38-O38-(L38*IF(L38<=79.99,20%,14%)+IF(L38<=79.99,4,IF(L38<=99.99,16,IF(L38<=199.99,20,IF(L38<=499.99,26,28)))))-L38*1.3%-L38*6%-(L38-O38)*9.25%-L38*3%-L38*3%-1) | Q38: =IF(AND(K38<>"",H38>0),(H38-K38)/H38,"") | U38: 100923 | W38: ambíguo: 215511 (77%) vs KIT4-AREIA-EDB-4KG-GF | X38: 13
A39: Jacartta | B39: Senspert - Erliquiose | C39: Sem variação | D39: 043 | E39: 14182727107 | F39: 0 | G39: NORMAL | H39: 145.8 | I39: 71.9 | J39: SIM | K39: 71.9 | L39: =IF(K39<>"",K39,I39) | O39: 51.04 | P39: =IF($O39="","",L39-O39-(L39*IF(L39<=79.99,20%,14%)+IF(L39<=79.99,4,IF(L39<=99.99,16,IF(L39<=199.99,20,IF(L39<=499.99,26,28)))))-L39*1.3%-L39*6%-(L39-O39)*9.25%-L39*3%-L39*3%-1) | Q39: =IF(AND(K39<>"",H39>0),(H39-K39)/H39,"") | R39: 909481504866304 | S39: 46144.387 | T39: 46295.438 | U39: 100942 | W39: custo preexistente (busca por texto) mantido
A40: Espaço De Bicho | B40: Kit Protetor De Colchão Lençol Oliver Home G Descartável Cadeira de Rodas Pós Operatório Impermeável | C40: KIT 3 - 15 UNIDADES | D40: 3PCT-PROTETOR-COLCHÃO | E40: 23593573884 | F40: 229413614023 | G40: NORMAL | H40: 89.9 | I40: 73.9 | J40: SIM | K40: 73.9 | L40: =IF(K40<>"",K40,I40) | M40: 3 | N40: 7.31 | O40: =ROUND(M40*N40,2) | P40: =IF($O40="","",L40-O40-(L40*IF(L40<=79.99,20%,14%)+IF(L40<=79.99,4,IF(L40<=99.99,16,IF(L40<=199.99,20,IF(L40<=499.99,26,28)))))-L40*1.3%-L40*6%-(L40-O40)*9.25%-L40*3%-L40*3%-1) | Q40: =IF(AND(K40<>"",H40>0),(H40-K40)/H40,"") | R40: 909477973245952 | S40: 46144.383 | T40: 46295.438 | U40: 101145 | V40: 213170 | W40: venda casada (1 pedido) · custo do KIT 213681 (3× 213170) | X40: 1 | Y40: ⚠ evidência fraca (1 pedido)
A41: Espaço De Bicho | B41: Kit Protetor De Colchão Lençol Oliver Home G Descartável Cadeira de Rodas Pós Operatório Impermeável | C41: KIT 5 - 25 UNIDADES | D41: 5PCT-PROTETOR-COLCHÃO | E41: 23593573884 | F41: 229413614025 | G41: NORMAL | H41: 120.9 | I41: 119.9 | J41: SIM | K41: 119.9 | L41: =IF(K41<>"",K41,I41) | M41: 5 | N41: 7.31 | O41: =ROUND(M41*N41,2) | P41: =IF($O41="","",L41-O41-(L41*IF(L41<=79.99,20%,14%)+IF(L41<=79.99,4,IF(L41<=99.99,16,IF(L41<=199.99,20,IF(L41<=499.99,26,28)))))-L41*1.3%-L41*6%-(L41-O41)*9.25%-L41*3%-L41*3%-1) | Q41: =IF(AND(K41<>"",H41>0),(H41-K41)/H41,"") | R41: 909477973245952 | S41: 46144.383 | T41: 46295.438 | U41: 101145 | V41: 213170 | W41: SKU do de-para · custo do KIT 213683 (5× 213170) | X41: 5 | Y41: ok
A42: Jacartta | B42: Escorredor De Louça Suspenso Aço Inoxidável Organizador Louça Preto 65cm | C42: Modelo 1 | D42: 214030 | E42: 23294523254 | F42: 219613010012 | G42: NORMAL | H42: 199.9 | I42: 74.9 | J42: SIM | K42: 74.9 | L42: =IF(K42<>"",K42,I42) | M42: 1 | N42: 51.63 | O42: =ROUND(M42*N42,2) | P42: =IF($O42="","",L42-O42-(L42*IF(L42<=79.99,20%,14%)+IF(L42<=79.99,4,IF(L42<=99.99,16,IF(L42<=199.99,20,IF(L42<=499.99,26,28)))))-L42*1.3%-L42*6%-(L42-O42)*9.25%-L42*3%-L42*3%-1) | Q42: =IF(AND(K42<>"",H42>0),(H42-K42)/H42,"") | R42: 478386871025791 | S42: 46209.646 | T42: 46326.999 | U42: 101224 | V42: 214030 | W42: venda casada (608 pedidos) | X42: 608 | Y42: ok
A43: Jacartta | B43: Gelo Artificial Reciclavél 1l | C43: Sem variação | D43: 0088 | E43: 9269606920 | F43: 0 | G43: NORMAL | H43: 26 | I43: 9.9 | J43: SIM | K43: 9.9 | L43: =IF(K43<>"",K43,I43) | O43: 7.02 | P43: =IF($O43="","",L43-O43-(L43*IF(L43<=79.99,20%,14%)+IF(L43<=79.99,4,IF(L43<=99.99,16,IF(L43<=199.99,20,IF(L43<=499.99,26,28)))))-L43*1.3%-L43*6%-(L43-O43)*9.25%-L43*3%-L43*3%-1) | Q43: =IF(AND(K43<>"",H43>0),(H43-K43)/H43,"") | R43: 1 | U43: 100712 | W43: custo preexistente (busca por texto) mantido
A44: Jacartta | B44: Kit Potes de Vidro 640ml/340ml Hermético Marmita Fit com Tampa 4 Travas | C44: 10 UNIDADES,640ML | D44: KIT10-640ML-SORTIDO | E44: 22299038596 | F44: 159549291898 | G44: NORMAL | H44: 199.9 | I44: 117.89 | J44: SIM | K44: 117.89 | L44: =IF(K44<>"",K44,I44) | M44: 10 | N44: =O44/M44 | O44: 67.4 | P44: =IF($O44="","",L44-O44-(L44*IF(L44<=79.99,20%,14%)+IF(L44<=79.99,4,IF(L44<=99.99,16,IF(L44<=199.99,20,IF(L44<=499.99,26,28)))))-L44*1.3%-L44*6%-(L44-O44)*9.25%-L44*3%-L44*3%-1) | Q44: =IF(AND(K44<>"",H44>0),(H44-K44)/H44,"") | R44: 492047266168992 | S44: 46248 | T44: 46249 | U44: 101220 | V44: 213877 | W44: venda casada (47 pedidos) · QTD/custo manuais mantidos | X44: 47 | Y44: ok
A45: Espaço De Bicho | B45: Laviz MO Pet Suplemento para Cães e Gatos Debilitados 30g | C45: Sem variação | D45: LAVIZ-M.O-PET-30G | E45: 20499252415 | F45: 0 | G45: NORMAL | H45: 89.9 | I45: 49.9 | J45: SIM | K45: 49.9 | L45: =IF(K45<>"",K45,I45) | P45: =IF($O45="","",L45-O45-(L45*IF(L45<=79.99,20%,14%)+IF(L45<=79.99,4,IF(L45<=99.99,16,IF(L45<=199.99,20,IF(L45<=499.99,26,28)))))-L45*1.3%-L45*6%-(L45-O45)*9.25%-L45*3%-L45*3%-1) | Q45: =IF(AND(K45<>"",H45>0),(H45-K45)/H45,"") | R45: 909477973245952 | S45: 46144.383 | T45: 46295.438 | U45: 100944 | V45: LAVIZ-M.O-PET-30G | W45: SKU idêntico na Olist · CUSTO ZERADO na Olist (conferido hoje) | Y45: ok
A46: Espaço De Bicho | B46: Máquina De Secar Pets Plus Grande Silencioso | C46: Sem variação | D46: CAIXA-SEC-PET | E46: 23097772664 | F46: 0 | G46: NORMAL | H46: 2500 | I46: 1239.9 | J46: SIM | K46: 1239.9 | L46: =IF(K46<>"",K46,I46) | M46: 1 | N46: 1003.09 | O46: =ROUND(M46*N46,2) | P46: =IF($O46="","",L46-O46-(L46*IF(L46<=79.99,20%,14%)+IF(L46<=79.99,4,IF(L46<=99.99,16,IF(L46<=199.99,20,IF(L46<=499.99,26,28)))))-L46*1.3%-L46*6%-(L46-O46)*9.25%-L46*3%-L46*3%-1) | Q46: =IF(AND(K46<>"",H46>0),(H46-K46)/H46,"") | R46: 909477973245952 | S46: 46144.383 | T46: 46295.438 | U46: 100929 | V46: 212900 | W46: venda casada (7 pedidos) | X46: 7 | Y46: ok
A47: Espaço De Bicho | B47: Meloxivet 1mg Pequeno Porte Anti-Inflamatório para Cães e Gatos Blister 10 comprimidos DUPRAT | C47: 1 MG | D47: MELOXIVET-1MG-10CPS | E47: 23594548218 | F47: 219613552027 | G47: NORMAL | H47: 99.9 | I47: 26.9 | J47: SIM | K47: 26.9 | L47: =IF(K47<>"",K47,I47) | M47: 1 | N47: 13.15 | O47: =ROUND(M47*N47,2) | P47: =IF($O47="","",L47-O47-(L47*IF(L47<=79.99,20%,14%)+IF(L47<=79.99,4,IF(L47<=99.99,16,IF(L47<=199.99,20,IF(L47<=499.99,26,28)))))-L47*1.3%-L47*6%-(L47-O47)*9.25%-L47*3%-L47*3%-1) | Q47: =IF(AND(K47<>"",H47>0),(H47-K47)/H47,"") | R47: 909477973245952 | S47: 46144.383 | T47: 46295.438 | U47: 100942 | V47: 213535 | W47: venda casada (2 pedidos) | X47: 2 | Y47: ok
A48: Espaço De Bicho | B48: Meloxivet 1mg Pequeno Porte Anti-Inflamatório para Cães e Gatos Blister 10 comprimidos DUPRAT | C48: 2 MG | D48: MELOXIVET-2MG-10CPS | E48: 23594548218 | F48: 219613552028 | G48: NORMAL | H48: 99.9 | I48: 32.9 | J48: SIM | K48: 32.9 | L48: =IF(K48<>"",K48,I48) | P48: =IF($O48="","",L48-O48-(L48*IF(L48<=79.99,20%,14%)+IF(L48<=79.99,4,IF(L48<=99.99,16,IF(L48<=199.99,20,IF(L48<=499.99,26,28)))))-L48*1.3%-L48*6%-(L48-O48)*9.25%-L48*3%-L48*3%-1) | Q48: =IF(AND(K48<>"",H48>0),(H48-K48)/H48,"") | R48: 909477973245952 | S48: 46144.383 | T48: 46295.438 | U48: 100942 | V48: MELOXIVET-2MG-10CPS | W48: SKU idêntico na Olist · CUSTO ZERADO na Olist (conferido hoje) | Y48: ok
A49: Espaço De Bicho | B49: Potrus 6 Kg - Lavizoo ( Suplmento P/ Crescimento De Potros ) | C49: Sem variação | D49: POTRUS-6KG | E49: 22592987404 | F49: 0 | G49: NORMAL | H49: 999.9 | I49: 904.9 | J49: SIM | K49: 904.9 | L49: =IF(K49<>"",K49,I49) | P49: =IF($O49="","",L49-O49-(L49*IF(L49<=79.99,20%,14%)+IF(L49<=79.99,4,IF(L49<=99.99,16,IF(L49<=199.99,20,IF(L49<=499.99,26,28)))))-L49*1.3%-L49*6%-(L49-O49)*9.25%-L49*3%-L49*3%-1) | Q49: =IF(AND(K49<>"",H49>0),(H49-K49)/H49,"") | R49: 909477973245952 | S49: 46144.383 | T49: 46295.438 | U49: 100910 | V49: POTRUS-6KG | W49: SKU idêntico na Olist · CUSTO ZERADO na Olist (conferido hoje) | Y49: ok
A50: Jacartta | B50: Kit 5/ kit 10 Potes de Vidro 640ml Hermético Marmita Fit com Tampa 4 Travas Oliver Home | C50: 10 UNIDADES,640ML | D50: KIT-10POTES-640ML | E50: 26695370644 | F50: 351245360246 | G50: NORMAL | H50: 189.9 | I50: 117.9 | J50: SIM | K50: 117.9 | L50: =IF(K50<>"",K50,I50) | M50: 10 | N50: =O50/M50 | O50: 67.4 | P50: =IF($O50="","",L50-O50-(L50*IF(L50<=79.99,20%,14%)+IF(L50<=79.99,4,IF(L50<=99.99,16,IF(L50<=199.99,20,IF(L50<=499.99,26,28)))))-L50*1.3%-L50*6%-(L50-O50)*9.25%-L50*3%-L50*3%-1) | Q50: =IF(AND(K50<>"",H50>0),(H50-K50)/H50,"") | R50: 478386871025791 | S50: 46209.646 | T50: 46326.999 | U50: 101220 | V50: 213877 | W50: venda casada (1 pedido) · QTD/custo manuais mantidos | X50: 1 | Y50: ⚠ evidência fraca (1 pedido)
A51: Espaço De Bicho | B51: Protetor De Colchão Lençol G 5 UNI Cadeira de Rodas Pós Operatório Impermeavél | C51: Sem variação | D51: 1PCT-PROTETOR-COLCHÃO | E51: 23098070610 | F51: 0 | G51: NORMAL | H51: 39.9 | I51: 39.9 | J51: NÃO | L51: =IF(K51<>"",K51,I51) | P51: =IF($O51="","",L51-O51-(L51*IF(L51<=79.99,20%,14%)+IF(L51<=79.99,4,IF(L51<=99.99,16,IF(L51<=199.99,20,IF(L51<=499.99,26,28)))))-L51*1.3%-L51*6%-(L51-O51)*9.25%-L51*3%-L51*3%-1) | Q51: =IF(AND(K51<>"",H51>0),(H51-K51)/H51,"") | U51: 101145 | V51: 1PCT-PROTETOR-COLCHÃO | W51: SKU idêntico na Olist · CUSTO ZERADO na Olist (conferido hoje) | Y51: ok
A52: Espaço De Bicho | B52: Regenerador Articular Fortflex C/ 30 Comp. P/ Cães E Gatos | C52: Sem variação | D52: FORTFLEX-30G | E52: 21797673900 | F52: 0 | G52: NORMAL | H52: 89.9 | I52: 64.9 | J52: SIM | K52: 64.9 | L52: =IF(K52<>"",K52,I52) | M52: 1 | N52: 29.73 | O52: =ROUND(M52*N52,2) | P52: =IF($O52="","",L52-O52-(L52*IF(L52<=79.99,20%,14%)+IF(L52<=79.99,4,IF(L52<=99.99,16,IF(L52<=199.99,20,IF(L52<=499.99,26,28)))))-L52*1.3%-L52*6%-(L52-O52)*9.25%-L52*3%-L52*3%-1) | Q52: =IF(AND(K52<>"",H52>0),(H52-K52)/H52,"") | R52: 909477973245952 | S52: 46144.383 | T52: 46295.438 | U52: 100944 | V52: 213629 | W52: venda casada (3 pedidos) | X52: 3 | Y52: ok
A53: Espaço De Bicho | B53: Remédio para carrapato cachorro e anti pulgas Confront Plus | C53: 10 A 20KG | D53: CONFRONT-PLUS-10A20KG | E53: 22493004901 | F53: 169708443633 | G53: NORMAL | H53: 59.9 | I53: 59.9 | J53: NÃO | L53: =IF(K53<>"",K53,I53) | P53: =IF($O53="","",L53-O53-(L53*IF(L53<=79.99,20%,14%)+IF(L53<=79.99,4,IF(L53<=99.99,16,IF(L53<=199.99,20,IF(L53<=499.99,26,28)))))-L53*1.3%-L53*6%-(L53-O53)*9.25%-L53*3%-L53*3%-1) | Q53: =IF(AND(K53<>"",H53>0),(H53-K53)/H53,"") | U53: 100942 | V53: CONFRONT-PLUS-10A20KG | W53: SKU idêntico na Olist · CUSTO ZERADO na Olist (conferido hoje) | Y53: ok
A54: Espaço De Bicho | B54: Remédio para carrapato cachorro e anti pulgas Confront Plus | C54: 40 A 60KG | D54: CONFRONT-PLUS-40A60KG | E54: 22493004901 | F54: 169708443635 | G54: NORMAL | H54: 59.9 | I54: 59.9 | J54: NÃO | L54: =IF(K54<>"",K54,I54) | P54: =IF($O54="","",L54-O54-(L54*IF(L54<=79.99,20%,14%)+IF(L54<=79.99,4,IF(L54<=99.99,16,IF(L54<=199.99,20,IF(L54<=499.99,26,28)))))-L54*1.3%-L54*6%-(L54-O54)*9.25%-L54*3%-L54*3%-1) | Q54: =IF(AND(K54<>"",H54>0),(H54-K54)/H54,"") | U54: 100942 | V54: CONFRONT-PLUS-40A60KG | W54: SKU idêntico na Olist · CUSTO ZERADO na Olist (conferido hoje) | Y54: ok
A55: Espaço De Bicho | B55: Sabonete Tiuran Sarnicida e Fungos Para Cães & Gatos 80g | C55: Sem variação | D55: SABONETE-TIURAN-80G | E55: 22299144399 | F55: 0 | G55: NORMAL | H55: 59.9 | I55: 19.9 | J55: SIM | K55: 19.9 | L55: =IF(K55<>"",K55,I55) | M55: 1 | N55: 8.4 | O55: =ROUND(M55*N55,2) | P55: =IF($O55="","",L55-O55-(L55*IF(L55<=79.99,20%,14%)+IF(L55<=79.99,4,IF(L55<=99.99,16,IF(L55<=199.99,20,IF(L55<=499.99,26,28)))))-L55*1.3%-L55*6%-(L55-O55)*9.25%-L55*3%-L55*3%-1) | Q55: =IF(AND(K55<>"",H55>0),(H55-K55)/H55,"") | R55: 909477973245952 | S55: 46144.383 | T55: 46295.438 | U55: 100929 | V55: 213397 | W55: venda casada (16 pedidos) | X55: 16 | Y55: ok
A56: Espaço De Bicho | B56: Solução Otológica Duprat Otospan Cães & Gatos - 10 Ml | C56: Sem variação | D56: OTOSPAN-10ML | E56: 23794617455 | F56: 0 | G56: NORMAL | H56: 69.9 | I56: 69.9 | J56: NÃO | L56: =IF(K56<>"",K56,I56) | P56: =IF($O56="","",L56-O56-(L56*IF(L56<=79.99,20%,14%)+IF(L56<=79.99,4,IF(L56<=99.99,16,IF(L56<=199.99,20,IF(L56<=499.99,26,28)))))-L56*1.3%-L56*6%-(L56-O56)*9.25%-L56*3%-L56*3%-1) | Q56: =IF(AND(K56<>"",H56>0),(H56-K56)/H56,"") | U56: 100942 | V56: OTOSPAN-10ML | W56: SKU idêntico na Olist · CUSTO ZERADO na Olist (conferido hoje) | Y56: ok
A57: Espaço De Bicho | B57: Gelo Artificial Reciclavél 1l | C57: Sem variação | D57: 0088 | E57: 51564773679 | F57: 0 | G57: NORMAL | H57: 26 | I57: 9.9 | J57: SIM | K57: 9.9 | L57: =IF(K57<>"",K57,I57) | O57: 7.02 | P57: =IF($O57="","",L57-O57-(L57*IF(L57<=79.99,20%,14%)+IF(L57<=79.99,4,IF(L57<=99.99,16,IF(L57<=199.99,20,IF(L57<=499.99,26,28)))))-L57*1.3%-L57*6%-(L57-O57)*9.25%-L57*3%-L57*3%-1) | Q57: =IF(AND(K57<>"",H57>0),(H57-K57)/H57,"") | R57: 909477973245952 | S57: 46144.383 | T57: 46295.438 | U57: 100712 | W57: custo preexistente (busca por texto) mantido
A58: Espaço De Bicho | B58: Tapete Higienico 150 unidades Espaço De Bicho Envio Imediato | C58: Sem variação | D58: 0839 | E58: 21172591510 | F58: 0 | G58: NORMAL | H58: 246.9 | I58: 164.9 | J58: SIM | K58: 164.9 | L58: =IF(K58<>"",K58,I58) | M58: 3 | N58: 33.1 | O58: =ROUND(M58*N58,2) | P58: =IF($O58="","",L58-O58-(L58*IF(L58<=79.99,20%,14%)+IF(L58<=79.99,4,IF(L58<=99.99,16,IF(L58<=199.99,20,IF(L58<=499.99,26,28)))))-L58*1.3%-L58*6%-(L58-O58)*9.25%-L58*3%-L58*3%-1) | Q58: =IF(AND(K58<>"",H58>0),(H58-K58)/H58,"") | R58: 909475783836672 | S58: 46144.379 | T58: 46295.438 | U58: 100926 | V58: EDB60X60-50UN | W58: venda casada (219 pedidos) · custo do KIT 212445 (3× EDB60X60-50UN) | X58: 219 | Y58: ok
A59: Espaço De Bicho | B59: Tapete Higiênico Espaço De Bicho 100 unidades Envio Imediato | C59: Sem variação | D59: 0838 | E59: 21472592049 | F59: 0 | G59: NORMAL | H59: 162.9 | I59: 114.9 | J59: SIM | K59: 114.9 | L59: =IF(K59<>"",K59,I59) | M59: 2 | N59: 33.1 | O59: =ROUND(M59*N59,2) | P59: =IF($O59="","",L59-O59-(L59*IF(L59<=79.99,20%,14%)+IF(L59<=79.99,4,IF(L59<=99.99,16,IF(L59<=199.99,20,IF(L59<=499.99,26,28)))))-L59*1.3%-L59*6%-(L59-O59)*9.25%-L59*3%-L59*3%-1) | Q59: =IF(AND(K59<>"",H59>0),(H59-K59)/H59,"") | R59: 909475783836672 | S59: 46144.379 | T59: 46295.438 | U59: 100926 | V59: EDB60X60-50UN | W59: venda casada (642 pedidos) · custo do KIT 212444 (2× EDB60X60-50UN) | X59: 642 | Y59: ok
A60: Espaço De Bicho | B60: Tapete Higiênico Espaço De Bicho 100 unidades Envio Imediato Promoção | C60: Sem variação | D60: Kit 100 Un Espaço | E60: 22292855878 | F60: 0 | G60: NORMAL | H60: 179.9 | I60: 129.9 | J60: SIM | K60: 129.9 | L60: =IF(K60<>"",K60,I60) | M60: 2 | N60: 33.1 | O60: =ROUND(M60*N60,2) | P60: =IF($O60="","",L60-O60-(L60*IF(L60<=79.99,20%,14%)+IF(L60<=79.99,4,IF(L60<=99.99,16,IF(L60<=199.99,20,IF(L60<=499.99,26,28)))))-L60*1.3%-L60*6%-(L60-O60)*9.25%-L60*3%-L60*3%-1) | Q60: =IF(AND(K60<>"",H60>0),(H60-K60)/H60,"") | R60: 909477973245952 | S60: 46144.383 | T60: 46295.438 | U60: 100926 | V60: EDB60X60-50UN | W60: venda casada (5 pedidos) · custo do KIT 212444 (2× EDB60X60-50UN) | X60: 5 | Y60: ok
A61: Jacartta | B61: Escorredor De Louça Suspenso Aço Inoxidável Organizador Louça Preto 65cm | C61: Modelo 3 | D61: 214032 | E61: 23294523254 | F61: 219613010014 | G61: NORMAL | H61: 199.9 | I61: 79.9 | J61: SIM | K61: 79.9 | L61: =IF(K61<>"",K61,I61) | M61: 1 | N61: 50.11 | O61: =ROUND(M61*N61,2) | P61: =IF($O61="","",L61-O61-(L61*IF(L61<=79.99,20%,14%)+IF(L61<=79.99,4,IF(L61<=99.99,16,IF(L61<=199.99,20,IF(L61<=499.99,26,28)))))-L61*1.3%-L61*6%-(L61-O61)*9.25%-L61*3%-L61*3%-1) | Q61: =IF(AND(K61<>"",H61>0),(H61-K61)/H61,"") | R61: 478386871025791 | S61: 46209.646 | T61: 46326.999 | U61: 101224 | V61: 214032 | W61: venda casada (15 pedidos) | X61: 15 | Y61: ok
A62: Espaço De Bicho | B62: Tapete Higiênico Espaço De Bicho P/ Cães E Gatos 60x60 Com 80 Unidades | C62: Sem variação | D62: 0835 | E62: 21772563384 | F62: 0 | G62: NORMAL | H62: 130.9 | I62: 79.9 | J62: SIM | K62: 79.9 | L62: =IF(K62<>"",K62,I62) | M62: 1 | N62: 19.58 | O62: =ROUND(M62*N62,2) | P62: =IF($O62="","",L62-O62-(L62*IF(L62<=79.99,20%,14%)+IF(L62<=79.99,4,IF(L62<=99.99,16,IF(L62<=199.99,20,IF(L62<=499.99,26,28)))))-L62*1.3%-L62*6%-(L62-O62)*9.25%-L62*3%-L62*3%-1) | Q62: =IF(AND(K62<>"",H62>0),(H62-K62)/H62,"") | R62: 909475783836672 | S62: 46144.379 | T62: 46295.438 | U62: 100926 | V62: 212952 | W62: venda casada (413 pedidos) · custo do KIT 213841 (1× 212952) | X62: 413 | Y62: ok
A63: Jacartta | B63: Cata caca saquinho coletor para Pet Ossinho | C63: Sem variação | D63: CATA-CACA | E63: 22598350613 | F63: 0 | G63: NORMAL | H63: 29.9 | I63: 29.9 | J63: NÃO | L63: =IF(K63<>"",K63,I63) | O63: 18.21 | P63: =IF($O63="","",L63-O63-(L63*IF(L63<=79.99,20%,14%)+IF(L63<=79.99,4,IF(L63<=99.99,16,IF(L63<=199.99,20,IF(L63<=499.99,26,28)))))-L63*1.3%-L63*6%-(L63-O63)*9.25%-L63*3%-L63*3%-1) | Q63: =IF(AND(K63<>"",H63>0),(H63-K63)/H63,"") | U63: 100927 | W63: custo preexistente (busca por texto) mantido
A64: Jacartta | B64: Balança Corporal Transparente Quadrada Digital Até 180kg Com Vidro Temperado Premium - OliverHome | C64: Balança Bioimpedância | D64: BALANÇA-BIOIMPEDANCIA | E64: 51464466694 | F64: 326244948679 | G64: NORMAL | H64: 84.9 | I64: 29.9 | J64: SIM | K64: 29.9 | L64: =IF(K64<>"",K64,I64) | N64: 17.16 | O64: =N64 | P64: =IF($O64="","",L64-O64-(L64*IF(L64<=79.99,20%,14%)+IF(L64<=79.99,4,IF(L64<=99.99,16,IF(L64<=199.99,20,IF(L64<=499.99,26,28)))))-L64*1.3%-L64*6%-(L64-O64)*9.25%-L64*3%-L64*3%-1) | Q64: =IF(AND(K64<>"",H64>0),(H64-K64)/H64,"") | R64: 478386871025791 | S64: 46209.646 | T64: 46326.999 | U64: 100122 | V64: 213282 | W64: venda casada (3 pedidos) · QTD/custo manuais mantidos | X64: 3 | Y64: ok
A65: Espaço De Bicho | B65: Provermin Envelope - Fembendazol - 20 G | C65: Sem variação | D65: 0896 | E65: 23614377779 | F65: 0 | G65: NORMAL | H65: 15.8 | I65: 7.99 | J65: SIM | K65: 7.99 | L65: =IF(K65<>"",K65,I65) | M65: 1 | N65: 3.11 | O65: =ROUND(M65*N65,2) | P65: =IF($O65="","",L65-O65-(L65*IF(L65<=79.99,20%,14%)+IF(L65<=79.99,4,IF(L65<=99.99,16,IF(L65<=199.99,20,IF(L65<=499.99,26,28)))))-L65*1.3%-L65*6%-(L65-O65)*9.25%-L65*3%-L65*3%-1) | Q65: =IF(AND(K65<>"",H65>0),(H65-K65)/H65,"") | R65: 909477973245952 | S65: 46144.383 | T65: 46295.438 | U65: 100944 | V65: 213139 | W65: venda casada (10 pedidos) | X65: 10 | Y65: ok
A66: Espaço De Bicho | B66: Tapete Higiênico Espaço De Bicho Shopito Oficial 100 Unidades Envio Imediato | C66: Sem variação | D66: 701 | E66: 22392897805 | F66: 0 | G66: NORMAL | H66: 189.9 | I66: 118.9 | J66: SIM | K66: 118.9 | L66: =IF(K66<>"",K66,I66) | M66: 2 | N66: 32.79 | O66: =ROUND(M66*N66,2) | P66: =IF($O66="","",L66-O66-(L66*IF(L66<=79.99,20%,14%)+IF(L66<=79.99,4,IF(L66<=99.99,16,IF(L66<=199.99,20,IF(L66<=499.99,26,28)))))-L66*1.3%-L66*6%-(L66-O66)*9.25%-L66*3%-L66*3%-1) | Q66: =IF(AND(K66<>"",H66>0),(H66-K66)/H66,"") | R66: 909474743648256 | S66: 46144.378 | T66: 46295.979 | U66: 100926 | V66: 212955 | W66: venda casada (310 pedidos) · custo do KIT 213814 (2× 212955) | X66: 310 | Y66: ok
A67: Espaço De Bicho | B67: Tapete Higienico Espaço De Bicho Shopito Oficial 200 Unidades Envio Imediato | C67: Sem variação | D67: KIT200-TAPETE-SHOPITOO | E67: 22792893401 | F67: 0 | G67: NORMAL | H67: 359.9 | I67: 224.9 | J67: SIM | K67: 224.9 | L67: =IF(K67<>"",K67,I67) | M67: 4 | N67: 32.79 | O67: =ROUND(M67*N67,2) | P67: =IF($O67="","",L67-O67-(L67*IF(L67<=79.99,20%,14%)+IF(L67<=79.99,4,IF(L67<=99.99,16,IF(L67<=199.99,20,IF(L67<=499.99,26,28)))))-L67*1.3%-L67*6%-(L67-O67)*9.25%-L67*3%-L67*3%-1) | Q67: =IF(AND(K67<>"",H67>0),(H67-K67)/H67,"") | R67: 909474743648256 | S67: 46144.378 | T67: 46295.979 | U67: 100926 | V67: 212955 | W67: venda casada (288 pedidos) · custo do KIT 212450 (4× 212955) | X67: 288 | Y67: ok
A68: Espaço De Bicho | B68: Tapete Higienico Espaço De Bicho Shopito Oficial 50 Unidades Envio Imediato | C68: Sem variação | D68: 704 | E68: 19799215321 | F68: 0 | G68: NORMAL | H68: 89.9 | I68: 61.9 | J68: SIM | K68: 61.9 | L68: =IF(K68<>"",K68,I68) | M68: 1 | N68: 32.79 | O68: =ROUND(M68*N68,2) | P68: =IF($O68="","",L68-O68-(L68*IF(L68<=79.99,20%,14%)+IF(L68<=79.99,4,IF(L68<=99.99,16,IF(L68<=199.99,20,IF(L68<=499.99,26,28)))))-L68*1.3%-L68*6%-(L68-O68)*9.25%-L68*3%-L68*3%-1) | Q68: =IF(AND(K68<>"",H68>0),(H68-K68)/H68,"") | R68: 909474743648256 | S68: 46144.378 | T68: 46295.979 | U68: 100926 | V68: 212955 | W68: venda casada (75 pedidos) · custo do KIT 213813 (1× 212955) | X68: 75 | Y68: ok
A69: Jacartta | B69: Escorredor De Louça Suspenso Aço Inoxidável Organizador Louça Preto 65cm | C69: Modelo 2 | D69: 214031 | E69: 23294523254 | F69: 219613010013 | G69: NORMAL | H69: 199.9 | I69: 79.9 | J69: SIM | K69: 79.9 | L69: =IF(K69<>"",K69,I69) | M69: 1 | N69: 48.6 | O69: =ROUND(M69*N69,2) | P69: =IF($O69="","",L69-O69-(L69*IF(L69<=79.99,20%,14%)+IF(L69<=79.99,4,IF(L69<=99.99,16,IF(L69<=199.99,20,IF(L69<=499.99,26,28)))))-L69*1.3%-L69*6%-(L69-O69)*9.25%-L69*3%-L69*3%-1) | Q69: =IF(AND(K69<>"",H69>0),(H69-K69)/H69,"") | R69: 478386871025791 | S69: 46209.646 | T69: 46326.999 | U69: 101224 | V69: 214031 | W69: venda casada (50 pedidos) | X69: 50 | Y69: ok
A70: Espaço De Bicho | B70: Promoção tapetes higiênicos Espaço De Bicho Lavanda 80x60 - com 60 unidades | C70: Sem variação | D70: KIT60-EDB-LAVANDA | E70: 23392585948 | F70: 0 | G70: NORMAL | H70: 139.9 | I70: 109.9 | J70: SIM | K70: 109.9 | L70: =IF(K70<>"",K70,I70) | M70: 2 | N70: 30.99 | O70: =ROUND(M70*N70,2) | P70: =IF($O70="","",L70-O70-(L70*IF(L70<=79.99,20%,14%)+IF(L70<=79.99,4,IF(L70<=99.99,16,IF(L70<=199.99,20,IF(L70<=499.99,26,28)))))-L70*1.3%-L70*6%-(L70-O70)*9.25%-L70*3%-L70*3%-1) | Q70: =IF(AND(K70<>"",H70>0),(H70-K70)/H70,"") | R70: 909475783836672 | S70: 46144.379 | T70: 46295.438 | U70: 100926 | V70: 212965 | W70: venda casada (1424 pedidos) · custo do KIT 212460 (2× 212965) | X70: 1424 | Y70: ok
A71: Espaço De Bicho | B71: Tapete Higiênico Fralda Cachorro Pet Good Pad 60x60 30un | C71: Sem variação | D71: 0770 | E71: 20535109638 | F71: 0 | G71: NORMAL | H71: 79.9 | I71: 41.9 | J71: SIM | K71: 41.9 | L71: =IF(K71<>"",K71,I71) | M71: 1 | N71: 26.19 | O71: =ROUND(M71*N71,2) | P71: =IF($O71="","",L71-O71-(L71*IF(L71<=79.99,20%,14%)+IF(L71<=79.99,4,IF(L71<=99.99,16,IF(L71<=199.99,20,IF(L71<=499.99,26,28)))))-L71*1.3%-L71*6%-(L71-O71)*9.25%-L71*3%-L71*3%-1) | Q71: =IF(AND(K71<>"",H71>0),(H71-K71)/H71,"") | R71: 909476899504128 | S71: 46144.381 | T71: 46295.438 | U71: 100926 | V71: 212959 | W71: venda casada (1 pedido) · custo do KIT 213822 (1× 212959) | X71: 1 | Y71: ⚠ MODELO: anúncio diz 60x60, Olist é 80x60 · evidência fraca (1 pedido)
A72: Espaço De Bicho | B72: Tapete Higiênico Good Pad com 30 unidades 80x60 | C72: Sem variação | D72: 0796 | E72: 18159169069 | F72: 0 | G72: NORMAL | H72: 109.9 | I72: 46.9 | J72: SIM | K72: 46.9 | L72: =IF(K72<>"",K72,I72) | M72: 1 | N72: 26.19 | O72: =ROUND(M72*N72,2) | P72: =IF($O72="","",L72-O72-(L72*IF(L72<=79.99,20%,14%)+IF(L72<=79.99,4,IF(L72<=99.99,16,IF(L72<=199.99,20,IF(L72<=499.99,26,28)))))-L72*1.3%-L72*6%-(L72-O72)*9.25%-L72*3%-L72*3%-1) | Q72: =IF(AND(K72<>"",H72>0),(H72-K72)/H72,"") | R72: 909476899504128 | S72: 46144.381 | T72: 46295.438 | U72: 101681 | V72: 212959 | W72: venda casada (18 pedidos) · custo do KIT 213822 (1× 212959) | X72: 18 | Y72: ok
A73: Espaço De Bicho | B73: Tapete Higienico Good Pad P/ Cães E Gatos 60x60 Com 30 | C73: Sem variação | D73: 0770 | E73: 18233619235 | F73: 0 | G73: NORMAL | H73: 79.9 | I73: 41.9 | J73: SIM | K73: 41.9 | L73: =IF(K73<>"",K73,I73) | M73: 1 | N73: 18.75 | O73: =ROUND(M73*N73,2) | P73: =IF($O73="","",L73-O73-(L73*IF(L73<=79.99,20%,14%)+IF(L73<=79.99,4,IF(L73<=99.99,16,IF(L73<=199.99,20,IF(L73<=499.99,26,28)))))-L73*1.3%-L73*6%-(L73-O73)*9.25%-L73*3%-L73*3%-1) | Q73: =IF(AND(K73<>"",H73>0),(H73-K73)/H73,"") | R73: 909476899504128 | S73: 46144.381 | T73: 46295.438 | U73: 100924 | V73: 212960 | W73: venda casada (41 pedidos) · custo do KIT 213829 (1× 212960) | X73: 41 | Y73: ok
A74: Espaço De Bicho | B74: Tapete Higiênico Para Cães Ultra Pads 60x60cm 30 un Carvão Cães e Gatos Petlike Original | C74: Sem variação | D74: 689 | E74: 20535109134 | F74: 0 | G74: NORMAL | H74: 145.8 | I74: 54.9 | J74: SIM | K74: 54.9 | L74: =IF(K74<>"",K74,I74) | M74: 1 | N74: 23.4 | O74: =ROUND(M74*N74,2) | P74: =IF($O74="","",L74-O74-(L74*IF(L74<=79.99,20%,14%)+IF(L74<=79.99,4,IF(L74<=99.99,16,IF(L74<=199.99,20,IF(L74<=499.99,26,28)))))-L74*1.3%-L74*6%-(L74-O74)*9.25%-L74*3%-L74*3%-1) | Q74: =IF(AND(K74<>"",H74>0),(H74-K74)/H74,"") | R74: 909477973245952 | S74: 46144.383 | T74: 46295.438 | U74: 100924 | V74: 212950 | W74: venda casada (16 pedidos) · custo do KIT 213854 (1× 212950) | X74: 16 | Y74: ok
A75: Espaço De Bicho | B75: Tapete Higienico Pet Good Pads 80x60 com com 60 Unidades | C75: Sem variação | D75: 0793 | E75: 18159160182 | F75: 0 | G75: NORMAL | H75: 219.9 | I75: 114.9 | J75: SIM | K75: 114.9 | L75: =IF(K75<>"",K75,I75) | M75: 2 | N75: 26.19 | O75: =ROUND(M75*N75,2) | P75: =IF($O75="","",L75-O75-(L75*IF(L75<=79.99,20%,14%)+IF(L75<=79.99,4,IF(L75<=99.99,16,IF(L75<=199.99,20,IF(L75<=499.99,26,28)))))-L75*1.3%-L75*6%-(L75-O75)*9.25%-L75*3%-L75*3%-1) | Q75: =IF(AND(K75<>"",H75>0),(H75-K75)/H75,"") | R75: 909476899504128 | S75: 46144.381 | T75: 46295.438 | U75: 100926 | V75: 212959 | W75: venda casada (1 pedido) · custo do KIT 212457 (2× 212959) | X75: 1 | Y75: ⚠ evidência fraca (1 pedido)
A76: Espaço De Bicho | B76: Tapete Higiênico Pet P/ Cães Ultra Espaço De Bicho Lavanda 80x60 90unid | C76: Sem variação | D76: 731 | E76: 22397358570 | F76: 0 | G76: NORMAL | H76: 229.9 | I76: 164.9 | J76: SIM | K76: 164.9 | L76: =IF(K76<>"",K76,I76) | M76: 3 | N76: 30.99 | O76: =ROUND(M76*N76,2) | P76: =IF($O76="","",L76-O76-(L76*IF(L76<=79.99,20%,14%)+IF(L76<=79.99,4,IF(L76<=99.99,16,IF(L76<=199.99,20,IF(L76<=499.99,26,28)))))-L76*1.3%-L76*6%-(L76-O76)*9.25%-L76*3%-L76*3%-1) | Q76: =IF(AND(K76<>"",H76>0),(H76-K76)/H76,"") | R76: 909475783836672 | S76: 46144.379 | T76: 46295.438 | U76: 100926 | V76: 212965 | W76: venda casada (26 pedidos) · custo do KIT 213801 (3× 212965) | X76: 26 | Y76: ok
... A78: Espaço De Bicho | B78: Tapete Higiênico Pet P/ Cães Ultra Pads Lavanda 80x60 90unid | C78: Sem variação | D78: 0790_3 | E78: 21872832364 | F78: 0 | G78: NORMAL | H78: 349.9 | I78: 189.9 | J78: SIM | K78: 189.9 | L78: =IF(K78<>"",K78,I78) | M78: 3 | N78: 29.19 | O78: =ROUND(M78*N78,2) | P78: =IF($O78="","",L78-O78-(L78*IF(L78<=79.99,20%,14%)+IF(L78<=79.99,4,IF(L78<=99.99,16,IF(L78<=199.99,20,IF(L78<=499.99,26,28)))))-L78*1.3%-L78*6%-(L78-O78)*9.25%-L78*3%-L78*3%-1) | Q78: =IF(AND(K78<>"",H78>0),(H78-K78)/H78,"") | R78: 909476899504128 | S78: 46144.381 | T78: 46295.438 | U78: 100926 | V78: 212967 | W78: venda casada (3 pedidos) · custo do KIT 213809 (3× 212967) | X78: 3 | Y78: ok
A79: Jacartta | B79: Kit Potes de Vidro 640ml/340ml Hermético Marmita Fit com Tampa 4 Travas | C79: 10 UNIDADES,370ML | D79: KIT10-370ML-SORTIDO | E79: 22299038596 | F79: 159549291897 | G79: NORMAL | H79: 199.9 | I79: 77.89 | J79: SIM | K79: 77.89 | L79: =IF(K79<>"",K79,I79) | M79: 10 | N79: 4.45 | O79: =N79*M79 | P79: =IF($O79="","",L79-O79-(L79*IF(L79<=79.99,20%,14%)+IF(L79<=79.99,4,IF(L79<=99.99,16,IF(L79<=199.99,20,IF(L79<=499.99,26,28)))))-L79*1.3%-L79*6%-(L79-O79)*9.25%-L79*3%-L79*3%-1) | Q79: =IF(AND(K79<>"",H79>0),(H79-K79)/H79,"") | R79: 492047266168992 | S79: 46248 | T79: 46249 | U79: 101220 | V79: 213875 | W79: venda casada (39 pedidos) · QTD/custo manuais mantidos · ATENÇÃO: Olist hoje diz 3.93 | X79: 39 | Y79: ok
A80: Jacartta | B80: Kit 5/ kit 10 Potes de Vidro 640ml Hermético Marmita Fit com Tampa 4 Travas Oliver Home | C80: 10 UNIDADES,370ML | D80: KIT-10POTES-370ML | E80: 26695370644 | F80: 351245360245 | G80: NORMAL | H80: 159.9 | I80: 77.9 | J80: SIM | K80: 77.9 | L80: =IF(K80<>"",K80,I80) | M80: 10 | N80: 4.45 | O80: =N80*M80 | P80: =IF($O80="","",L80-O80-(L80*IF(L80<=79.99,20%,14%)+IF(L80<=79.99,4,IF(L80<=99.99,16,IF(L80<=199.99,20,IF(L80<=499.99,26,28)))))-L80*1.3%-L80*6%-(L80-O80)*9.25%-L80*3%-L80*3%-1) | Q80: =IF(AND(K80<>"",H80>0),(H80-K80)/H80,"") | R80: 478386871025791 | S80: 46209.646 | T80: 46326.999 | U80: 101220 | V80: 213876 | W80: SKU do de-para · QTD/custo manuais mantidos · ATENÇÃO: Olist hoje diz 3.93 | X80: 1349 | Y80: ok
A81: Espaço De Bicho | B81: Tapetes Higiênico Para Cachorro 60x60 - Kit 100 Unidades | C81: Sem variação | D81: 0771-100un | E81: 20233617726 | F81: 0 | G81: NORMAL | H81: 259.8 | I81: 117.9 | J81: SIM | K81: 117.9 | L81: =IF(K81<>"",K81,I81) | M81: 2 | N81: 33.46 | O81: =ROUND(M81*N81,2) | P81: =IF($O81="","",L81-O81-(L81*IF(L81<=79.99,20%,14%)+IF(L81<=79.99,4,IF(L81<=99.99,16,IF(L81<=199.99,20,IF(L81<=499.99,26,28)))))-L81*1.3%-L81*6%-(L81-O81)*9.25%-L81*3%-L81*3%-1) | Q81: =IF(AND(K81<>"",H81>0),(H81-K81)/H81,"") | R81: 909476899504128 | S81: 46144.381 | T81: 46295.438 | U81: 100926 | V81: 212961 | W81: venda casada (126 pedidos) · custo do KIT 212451 (2× 212961) | X81: 126 | Y81: ok
A82: Espaço De Bicho | B82: Tiuran 30mL - Sarnicida e Fungicida P/ Cães e Gatos | C82: Sem variação | D82: TIURAN-SOLUCAO-30ML | E82: 22294647847 | F82: 0 | G82: NORMAL | H82: 69.9 | I82: 20.31 | J82: SIM | K82: 20.31 | L82: =IF(K82<>"",K82,I82) | P82: =IF($O82="","",L82-O82-(L82*IF(L82<=79.99,20%,14%)+IF(L82<=79.99,4,IF(L82<=99.99,16,IF(L82<=199.99,20,IF(L82<=499.99,26,28)))))-L82*1.3%-L82*6%-(L82-O82)*9.25%-L82*3%-L82*3%-1) | Q82: =IF(AND(K82<>"",H82>0),(H82-K82)/H82,"") | R82: 909477973245952 | S82: 46144.383 | T82: 46295.438 | U82: 100942 | V82: TIURAN-SOLUCAO-30ML | W82: SKU idêntico na Olist · CUSTO ZERADO na Olist (conferido hoje) | Y82: ok
A83: Espaço De Bicho | B83: Tiuran Aerossol + Sabonete + Solução 30ml Sarnicida Fungicida Remédio para Sarna de Cachorro e Gato | C83: Kit 1 | D83: KIT-TIURAN-1AEROSSOL-1SABONETE-1SOLUÇÃO-30ML | E83: 21398316412 | F83: 179409556638 | G83: NORMAL | H83: 150.9 | I83: 70.9 | J83: SIM | K83: 70.9 | L83: =IF(K83<>"",K83,I83) | P83: =IF($O83="","",L83-O83-(L83*IF(L83<=79.99,20%,14%)+IF(L83<=79.99,4,IF(L83<=99.99,16,IF(L83<=199.99,20,IF(L83<=499.99,26,28)))))-L83*1.3%-L83*6%-(L83-O83)*9.25%-L83*3%-L83*3%-1) | Q83: =IF(AND(K83<>"",H83>0),(H83-K83)/H83,"") | R83: 909477973245952 | S83: 46144.383 | T83: 46295.438 | U83: 100942 | V83: KIT-TIURAN-1AEROSSOL-1SABONETE-1SOLUÇÃO-30ML | W83: SKU idêntico na Olist · CUSTO ZERADO na Olist (conferido hoje) | Y83: ok
A84: Espaço De Bicho | B84: Tiuran Aerossol 125ml Contra Sarna Fungo Cães e Gatos Duprat | C84: Sem variação | D84: TIURAN-AEROSOL-125ML | E84: 22894623213 | F84: 0 | G84: NORMAL | H84: 99.9 | I84: 40.99 | J84: SIM | K84: 40.99 | L84: =IF(K84<>"",K84,I84) | M84: 1 | N84: 19.5 | O84: =ROUND(M84*N84,2) | P84: =IF($O84="","",L84-O84-(L84*IF(L84<=79.99,20%,14%)+IF(L84<=79.99,4,IF(L84<=99.99,16,IF(L84<=199.99,20,IF(L84<=499.99,26,28)))))-L84*1.3%-L84*6%-(L84-O84)*9.25%-L84*3%-L84*3%-1) | Q84: =IF(AND(K84<>"",H84>0),(H84-K84)/H84,"") | R84: 909477973245952 | S84: 46144.383 | T84: 46295.438 | U84: 100942 | V84: 213451 | W84: venda casada (1 pedido) | X84: 1 | Y84: ⚠ evidência fraca (1 pedido)
A85: Espaço De Bicho | B85: Tiuran Solucao 100ml - Duprat sarnicida e fungicida | C85: Sem variação | D85: TIURAN-SOLUCAO-100 ML | E85: 22994628113 | F85: 0 | G85: NORMAL | H85: 79.9 | I85: 31.08 | J85: SIM | K85: 31.08 | L85: =IF(K85<>"",K85,I85) | M85: 1 | N85: 13.8 | O85: =ROUND(M85*N85,2) | P85: =IF($O85="","",L85-O85-(L85*IF(L85<=79.99,20%,14%)+IF(L85<=79.99,4,IF(L85<=99.99,16,IF(L85<=199.99,20,IF(L85<=499.99,26,28)))))-L85*1.3%-L85*6%-(L85-O85)*9.25%-L85*3%-L85*3%-1) | Q85: =IF(AND(K85<>"",H85>0),(H85-K85)/H85,"") | R85: 909477973245952 | S85: 46144.383 | T85: 46295.438 | U85: 100942 | V85: 212969 | W85: venda casada (1 pedido) | X85: 1 | Y85: ⚠ evidência fraca (1 pedido)
A86: Espaço De Bicho | B86: Triflex Solução Otológica 100 ml – Limpeza de Ouvidos para Cães e Gatos | Duprat | C86: Sem variação | D86: TRIFLEX-100 ML | E86: 23599119510 | F86: 0 | G86: NORMAL | H86: 89.9 | I86: 31.95 | J86: SIM | K86: 31.95 | L86: =IF(K86<>"",K86,I86) | M86: 1 | N86: 11.8 | O86: =ROUND(M86*N86,2) | P86: =IF($O86="","",L86-O86-(L86*IF(L86<=79.99,20%,14%)+IF(L86<=79.99,4,IF(L86<=99.99,16,IF(L86<=199.99,20,IF(L86<=499.99,26,28)))))-L86*1.3%-L86*6%-(L86-O86)*9.25%-L86*3%-L86*3%-1) | Q86: =IF(AND(K86<>"",H86>0),(H86-K86)/H86,"") | R86: 909477973245952 | S86: 46144.383 | T86: 46295.438 | U86: 100942 | V86: 213415 | W86: venda casada (4 pedidos) | X86: 4 | Y86: ok
A87: Espaço De Bicho | B87: Vermifugo Pulga Carrapato Sarna verme Ivercanis 12mg Até 60kg (1/2 para ate 30 kilos) | C87: Sem variação | D87: IVERCANIS-12MG | E87: 54864931430 | F87: 0 | G87: NORMAL | H87: 59.9 | I87: 59.9 | J87: NÃO | L87: =IF(K87<>"",K87,I87) | P87: =IF($O87="","",L87-O87-(L87*IF(L87<=79.99,20%,14%)+IF(L87<=79.99,4,IF(L87<=99.99,16,IF(L87<=199.99,20,IF(L87<=499.99,26,28)))))-L87*1.3%-L87*6%-(L87-O87)*9.25%-L87*3%-L87*3%-1) | Q87: =IF(AND(K87<>"",H87>0),(H87-K87)/H87,"") | U87: 100942 | V87: IVERCANIS-12MG | W87: SKU idêntico na Olist · CUSTO ZERADO na Olist (conferido hoje) | Y87: ok
A88: Espaço De Bicho | B88: Vetoryl 10mg 30 Cápsulas Dechra Trilostano Cães | C88: 30 Capsulas | D88: 0076 | E88: 21027927360 | F88: 199617148563 | G88: NORMAL | H88: 499.9 | I88: 349.9 | J88: SIM | K88: 349.9 | L88: =IF(K88<>"",K88,I88) | M88: 1 | N88: 197.58 | O88: =ROUND(M88*N88,2) | P88: =IF($O88="","",L88-O88-(L88*IF(L88<=79.99,20%,14%)+IF(L88<=79.99,4,IF(L88<=99.99,16,IF(L88<=199.99,20,IF(L88<=499.99,26,28)))))-L88*1.3%-L88*6%-(L88-O88)*9.25%-L88*3%-L88*3%-1) | Q88: =IF(AND(K88<>"",H88>0),(H88-K88)/H88,"") | R88: 909477973245952 | S88: 46144.383 | T88: 46295.438 | U88: 100008 | V88: 214928 | W88: venda casada (5 pedidos) · custo do KIT 214934 (1× 214928) | X88: 5 | Y88: ok
A89: Jacartta | B89: 2x Tapete Higiênico Fralda Pet Good Pad 60x60 60un | C89: Sem variação | D89: 0770 | E89: 20339081685 | F89: 0 | G89: NORMAL | H89: 299.8 | I89: 78.9 | J89: SIM | K89: 78.9 | L89: =IF(K89<>"",K89,I89) | M89: 2 | N89: 18.75 | O89: =ROUND(M89*N89,2) | P89: =IF($O89="","",L89-O89-(L89*IF(L89<=79.99,20%,14%)+IF(L89<=79.99,4,IF(L89<=99.99,16,IF(L89<=199.99,20,IF(L89<=499.99,26,28)))))-L89*1.3%-L89*6%-(L89-O89)*9.25%-L89*3%-L89*3%-1) | Q89: =IF(AND(K89<>"",H89>0),(H89-K89)/H89,"") | R89: 909481504866304 | S89: 46144.387 | T89: 46295.438 | U89: 100926 | V89: 212960 | W89: venda casada (1 pedido) · custo do KIT 213831 (2× 212960) | X89: 1 | Y89: ⚠ evidência fraca (1 pedido)
A90: Jacartta | B90: 3 Rolos Removedor De Pelos Pet de Gato e Cachorro Removedor de pelos | C90: 2 Unidades | D90: 854 | E90: 23494514165 | F90: 189180496161 | G90: NORMAL | H90: 89.9 | I90: 37.9 | J90: SIM | K90: 37.9 | L90: =IF(K90<>"",K90,I90) | P90: =IF($O90="","",L90-O90-(L90*IF(L90<=79.99,20%,14%)+IF(L90<=79.99,4,IF(L90<=99.99,16,IF(L90<=199.99,20,IF(L90<=499.99,26,28)))))-L90*1.3%-L90*6%-(L90-O90)*9.25%-L90*3%-L90*3%-1) | Q90: =IF(AND(K90<>"",H90>0),(H90-K90)/H90,"") | R90: 478386871025791 | S90: 46209.646 | T90: 46326.999 | U90: 100419 | W90: sem correspondência
A91: Jacartta | B91: Antitóxico Duprat Oral 20ML Cães Gatos | C91: Sem variação | D91: ANTITOXICO-DUPRAT-ORAL-20 ML | E91: 22794532158 | F91: 0 | G91: NORMAL | H91: 59.9 | I91: 18.83 | J91: SIM | K91: 18.83 | L91: =IF(K91<>"",K91,I91) | P91: =IF($O91="","",L91-O91-(L91*IF(L91<=79.99,20%,14%)+IF(L91<=79.99,4,IF(L91<=99.99,16,IF(L91<=199.99,20,IF(L91<=499.99,26,28)))))-L91*1.3%-L91*6%-(L91-O91)*9.25%-L91*3%-L91*3%-1) | Q91: =IF(AND(K91<>"",H91>0),(H91-K91)/H91,"") | R91: 909481504866304 | S91: 46144.387 | T91: 46295.438 | U91: 100942 | V91: ANTITOXICO-DUPRAT-ORAL-20 ML | W91: SKU idêntico na Olist · CUSTO ZERADO na Olist (conferido hoje) | Y91: ok
A92: Jacartta | B92: Kit Potes de Vidro 370ml Hermético Marmita Fit com Tampa 4 Travas | C92: 10 Potes,Azul | D92: KIT10-370ML-AZUL | E92: 23994504847 | F92: 209180481802 | G92: NORMAL | H92: 159.9 | I92: 77.9 | J92: SIM | K92: 77.9 | L92: =IF(K92<>"",K92,I92) | M92: 10 | N92: 4.45 | O92: =N92*M92 | P92: =IF($O92="","",L92-O92-(L92*IF(L92<=79.99,20%,14%)+IF(L92<=79.99,4,IF(L92<=99.99,16,IF(L92<=199.99,20,IF(L92<=499.99,26,28)))))-L92*1.3%-L92*6%-(L92-O92)*9.25%-L92*3%-L92*3%-1) | Q92: =IF(AND(K92<>"",H92>0),(H92-K92)/H92,"") | R92: 478386871025791 | S92: 46209.646 | T92: 46326.999 | U92: 101220 | V92: 213876 | W92: venda casada (271 pedidos) · QTD/custo manuais mantidos · ATENÇÃO: Olist hoje diz 3.93 | X92: 271 | Y92: ok
A93: Jacartta | B93: Assento Sanitário Almofadado Modelo Plus Slim Oval - OLIVER HOME | C93: Preto | D93: 2496 | E93: 20098318443 | F93: 199183060499 | G93: NORMAL | H93: 69.9 | I93: 44.89 | J93: SIM | K93: 44.89 | L93: =IF(K93<>"",K93,I93) | M93: 1 | N93: 15.26 | O93: =ROUND(M93*N93,2) | P93: =IF($O93="","",L93-O93-(L93*IF(L93<=79.99,20%,14%)+IF(L93<=79.99,4,IF(L93<=99.99,16,IF(L93<=199.99,20,IF(L93<=499.99,26,28)))))-L93*1.3%-L93*6%-(L93-O93)*9.25%-L93*3%-L93*3%-1) | Q93: =IF(AND(K93<>"",H93>0),(H93-K93)/H93,"") | R93: 492047266168992 | S93: 46248 | T93: 46249 | U93: 101131 | V93: 213990 | W93: venda casada (22 pedidos) | X93: 22 | Y93: ok
A94: Jacartta | B94: Kit Potes de Vidro 370ml Hermético Marmita Fit com Tampa 4 Travas | C94: 10 Potes,Branco | D94: KIT10-370ML-BRANCO | E94: 23994504847 | F94: 209180481801 | G94: NORMAL | H94: 159.9 | I94: 77.9 | J94: SIM | K94: 77.9 | L94: =IF(K94<>"",K94,I94) | M94: 10 | N94: 4.45 | O94: =N94*M94 | P94: =IF($O94="","",L94-O94-(L94*IF(L94<=79.99,20%,14%)+IF(L94<=79.99,4,IF(L94<=99.99,16,IF(L94<=199.99,20,IF(L94<=499.99,26,28)))))-L94*1.3%-L94*6%-(L94-O94)*9.25%-L94*3%-L94*3%-1) | Q94: =IF(AND(K94<>"",H94>0),(H94-K94)/H94,"") | R94: 478386871025791 | S94: 46209.646 | T94: 46326.999 | U94: 101220 | V94: 213875 | W94: venda casada (783 pedidos) · QTD/custo manuais mantidos · ATENÇÃO: Olist hoje diz 3.93 | X94: 783 | Y94: ok
A95: Jacartta | B95: Balanca De Cozinha Digital Alta Precisao 10kg Com Pilhas Inclusas AA OliverHome | C95: Sem variação | D95: BALANÇA-COZ | E95: 22399029506 | F95: 0 | G95: NORMAL | H95: 39.9 | I95: 19.9 | J95: SIM | K95: 19.9 | L95: =IF(K95<>"",K95,I95) | M95: 1 | N95: 6.26 | O95: =ROUND(M95*N95,2) | P95: =IF($O95="","",L95-O95-(L95*IF(L95<=79.99,20%,14%)+IF(L95<=79.99,4,IF(L95<=99.99,16,IF(L95<=199.99,20,IF(L95<=499.99,26,28)))))-L95*1.3%-L95*6%-(L95-O95)*9.25%-L95*3%-L95*3%-1) | Q95: =IF(AND(K95<>"",H95>0),(H95-K95)/H95,"") | R95: 478386871025791 | S95: 46209.646 | T95: 46326.999 | U95: 101234 | V95: 213242 | W95: venda casada (9 pedidos) · custo do KIT 213991 (1× 213242) | X95: 9 | Y95: ok
A96: Jacartta | B96: Balança Digital Medidora Corporal Bioimpedância até 180kg OliverHome | C96: Balança Bioimpedância | D96: BALANÇA-BIOIMPEDANCIA | E96: 23798986920 | F96: 228792593644 | G96: NORMAL | H96: 69.9 | I96: 29.9 | J96: SIM | K96: 29.9 | L96: =IF(K96<>"",K96,I96) | M96: 1 | N96: 17.16 | O96: =ROUND(M96*N96,2) | P96: =IF($O96="","",L96-O96-(L96*IF(L96<=79.99,20%,14%)+IF(L96<=79.99,4,IF(L96<=99.99,16,IF(L96<=199.99,20,IF(L96<=499.99,26,28)))))-L96*1.3%-L96*6%-(L96-O96)*9.25%-L96*3%-L96*3%-1) | Q96: =IF(AND(K96<>"",H96>0),(H96-K96)/H96,"") | R96: 478386871025791 | S96: 46209.646 | T96: 46326.999 | U96: 100122 | V96: 213282 | W96: venda casada (6900 pedidos) · custo do KIT 213992 (1× 213282) | X96: 6900 | Y96: ok
A97: Jacartta | B97: Balança Digital Medidora Corporal Bioimpedância até 180kg OliverHome | C97: Balança de Cozinha | D97: BALANÇA-COZINHA | E97: 23798986920 | F97: 228792593645 | G97: NORMAL | H97: 49.9 | I97: 23.9 | J97: SIM | K97: 23.9 | L97: =IF(K97<>"",K97,I97) | M97: 1 | N97: 6.26 | O97: =ROUND(M97*N97,2) | P97: =IF($O97="","",L97-O97-(L97*IF(L97<=79.99,20%,14%)+IF(L97<=79.99,4,IF(L97<=99.99,16,IF(L97<=199.99,20,IF(L97<=499.99,26,28)))))-L97*1.3%-L97*6%-(L97-O97)*9.25%-L97*3%-L97*3%-1) | Q97: =IF(AND(K97<>"",H97>0),(H97-K97)/H97,"") | R97: 478386871025791 | S97: 46209.646 | T97: 46326.999 | U97: 100122 | V97: 213242 | W97: venda casada (110 pedidos) · custo do KIT 213991 (1× 213242) | X97: 110 | Y97: ok
A98: Jacartta | B98: Bebedouro Beija Flor Luxo com chapéu e poleiro - Jelplast Sortido | C98: Sem variação | D98: BEBEDOURO-BEIJAFLOR | E98: 23597344048 | F98: 0 | G98: NORMAL | H98: 29.9 | I98: 13.9 | J98: SIM | K98: 13.9 | L98: =IF(K98<>"",K98,I98) | M98: 1 | N98: 3.35 | O98: =ROUND(M98*N98,2) | P98: =IF($O98="","",L98-O98-(L98*IF(L98<=79.99,20%,14%)+IF(L98<=79.99,4,IF(L98<=99.99,16,IF(L98<=199.99,20,IF(L98<=499.99,26,28)))))-L98*1.3%-L98*6%-(L98-O98)*9.25%-L98*3%-L98*3%-1) | Q98: =IF(AND(K98<>"",H98>0),(H98-K98)/H98,"") | R98: 909481504866304 | S98: 46144.387 | T98: 46295.438 | U98: 100916 | V98: 212811 | W98: venda casada (5 pedidos) | X98: 5 | Y98: ok
A99: Jacartta | B99: Bolinha Com Guizo Brinquedo Para Gato Colorido | C99: Sem variação | D99: BOLA-GUIZO-CAT | E99: 22993543151 | F99: 0 | G99: NORMAL | H99: 19.9 | I99: 9.9 | J99: SIM | K99: 9.9 | L99: =IF(K99<>"",K99,I99) | M99: 1 | N99: 0.2 | O99: =ROUND(M99*N99,2) | P99: =IF($O99="","",L99-O99-(L99*IF(L99<=79.99,20%,14%)+IF(L99<=79.99,4,IF(L99<=99.99,16,IF(L99<=199.99,20,IF(L99<=499.99,26,28)))))-L99*1.3%-L99*6%-(L99-O99)*9.25%-L99*3%-L99*3%-1) | Q99: =IF(AND(K99<>"",H99>0),(H99-K99)/H99,"") | R99: 909481504866304 | S99: 46144.387 | T99: 46295.438 | U99: 101926 | V99: 212992 | W99: venda casada (2 pedidos) | X99: 2 | Y99: ok
A100: Jacartta | B100: Bomba Submersa Bivolt Silenciosa - 220 L Ideal para Aquários, Fontes e Bebedouros Pet | C100: 110V | D100: BOMBA-200L-110V | E100: 23199011835 | F100: 169409852308 | G100: NORMAL | H100: 49.9 | I100: 49.9 | J100: NÃO | L100: =IF(K100<>"",K100,I100) | M100: 1 | N100: 8.26 | O100: =ROUND(M100*N100,2) | P100: =IF($O100="","",L100-O100-(L100*IF(L100<=79.99,20%,14%)+IF(L100<=79.99,4,IF(L100<=99.99,16,IF(L100<=199.99,20,IF(L100<=499.99,26,28)))))-L100*1.3%-L100*6%-(L100-O100)*9.25%-L100*3%-L100*3%-1) | Q100: =IF(AND(K100<>"",H100>0),(H100-K100)/H100,"") | U100: 100921 | V100: 214109 | W100: venda casada (238 pedidos) | X100: 238 | Y100: ok
A101: Jacartta | B101: Bomba Submersa Bivolt Silenciosa - 220 L Ideal para Aquários, Fontes e Bebedouros Pet | C101: 220V | D101: BOMBA-200L-220V | E101: 23199011835 | F101: 169409852309 | G101: NORMAL | H101: 49.9 | I101: 21.49 | J101: SIM | K101: 21.49 | L101: =IF(K101<>"",K101,I101) | M101: 1 | N101: 8.26 | O101: =ROUND(M101*N101,2) | P101: =IF($O101="","",L101-O101-(L101*IF(L101<=79.99,20%,14%)+IF(L101<=79.99,4,IF(L101<=99.99,16,IF(L101<=199.99,20,IF(L101<=499.99,26,28)))))-L101*1.3%-L101*6%-(L101-O101)*9.25%-L101*3%-L101*3%-1) | Q101: =IF(AND(K101<>"",H101>0),(H101-K101)/H101,"") | R101: 492047266168992 | S101: 46248 | T101: 46249 | U101: 100921 | V101: 214112 | W101: venda casada (198 pedidos) | X101: 198 | Y101: ok
...
