Workbook

Sheet Leia-me
A1: Curva ABC de Vendas por Item (SKU)
A2: Gerado em 24/07/2026, a partir do banco do Oráculo (Supabase), tabela olist_order_items.
A4: PERÍODO DISPONÍVEL — leia com atenção:
A5: • Foi pedida a curva dos últimos 3 e 6 meses. A base do Oráculo só tem pedidos desde 01/05/2026
A6: e itens por SKU desde 13/05/2026. Portanto NÃO existe janela de 6 meses: a curva abaixo cobre
A7: todo o período disponível (13/05/2026 a 24/07/2026, ~2,4 meses), que é também a melhor
A8: aproximação possível de "últimos 3 meses".
A10: COBERTURA PARCIAL DE ITENS:
A11: • Maio: cobertura de itens por SKU é residual (165 linhas para ~89 mil pedidos) — o mês pesa quase
A12: nada na curva. Junho e julho têm cobertura parcial (~46-53% dos pedidos com itens vinculados).
A13: • A curva reflete os pedidos COM itens vinculados; o ranking relativo tende a ser representativo,
A14: mas os valores absolutos subestimam o total vendido.
... A22: • 620 SKUs · 119.746 linhas de item · 117.025 pedidos com itens · receita total R$ 11.540.222,43

Sheet Curva ABC
A1: # | B1: SKU | C1: Produto | D1: Qtd Mai/26 | E1: Qtd Jun/26 | F1: Qtd Jul/26 (até 24) | G1: Qtd Total | H1: Receita Mai/26 | I1: Receita Jun/26 | J1: Receita Jul/26 (até 24) | K1: Receita Total | L1: % Receita | M1: % Acumulado | N1: Classe
A2: 1 | B2: 213986 | C2: CHALEIRA ELETRICA INOX E MODERNA - INOX - 110V | D2: 6 | E2: 9919 | F2: 5849 | G2: =SUM(D2:F2) | H2: 599.4 | I2: 891111.11 | J2: 461348 | K2: =SUM(H2:J2) | L2: =IF($K$622=0,0,K2/$K$622) | M2: =L2 | N2: =IF(M2<=0.8,"A",IF(M2<=0.95,"B","C"))
A3: 2 | B3: 214013 | C3: KIT CABIDE VELUDO PARA ROUPAS ADULTO - PRETO - 50 | D3: 0 | E3: 2032 | F3: 4761 | G3: =SUM(D3:F3) | H3: 0 | I3: 153102.11 | J3: 408443.98 | K3: =SUM(H3:J3) | L3: =IF($K$622=0,0,K3/$K$622) | M3: =M2+L3 | N3: =IF(M3<=0.8,"A",IF(M3<=0.95,"B","C"))
A4: 3 | B4: 213987 | C4: CHALEIRA ELETRICA - INOX - 220V | D4: 2 | E4: 3447 | F4: 3099 | G4: =SUM(D4:F4) | H4: 147.81 | I4: 302994.19 | J4: 238305.87 | K4: =SUM(H4:J4) | L4: =IF($K$622=0,0,K4/$K$622) | M4: =M3+L4 | N4: =IF(M4<=0.8,"A",IF(M4<=0.95,"B","C"))
A5: 4 | B5: 215515 | C5: KIT AREIA HIGIÊNCIA ESPAÇO DE BICHO - GRÃOS FINOS - 8KG | D5: 4 | E5: 3217 | F5: 1845 | G5: =SUM(D5:F5) | H5: 339.6 | I5: 298725.48 | J5: 187350.02 | K5: =SUM(H5:J5) | L5: =IF($K$622=0,0,K5/$K$622) | M5: =M4+L5 | N5: =IF(M5<=0.8,"A",IF(M5<=0.95,"B","C"))
A6: 5 | B6: EDB60X60-50UN | C6: TAPETE HIG ESPACO DE BICHO 60X60 50UN | D6: 77 | E6: 2714 | F6: 2484 | G6: =SUM(D6:F6) | H6: 4924.37 | I6: 177567.2 | J6: 153271.74 | K6: =SUM(H6:J6) | L6: =IF($K$622=0,0,K6/$K$622) | M6: =M5+L6 | N6: =IF(M6<=0.8,"A",IF(M6<=0.95,"B","C"))
A7: 6 | B7: 214014 | C7: KIT CABIDE VELUDO PARA ROUPAS ADULTO - CINZA - 50 | D7: 0 | E7: 988 | F7: 2410 | G7: =SUM(D7:F7) | H7: 0 | I7: 74678.58 | J7: 219343.62 | K7: =SUM(H7:J7) | L7: =IF($K$622=0,0,K7/$K$622) | M7: =M6+L7 | N7: =IF(M7<=0.8,"A",IF(M7<=0.95,"B","C"))
A8: 7 | B8: 213800 | C8: KIT TAPETE HIG ESPAÇO DE BICHO LAVANDA 80X60 - 60 UNIDADES | D8: 0 | E8: 885 | F8: 1126 | G8: =SUM(D8:F8) | H8: 0 | I8: 106771.5 | J8: 137652.4 | K8: =SUM(H8:J8) | L8: =IF($K$622=0,0,K8/$K$622) | M8: =M7+L8 | N8: =IF(M8<=0.8,"A",IF(M8<=0.95,"B","C"))
A9: 8 | B9: 214162 | C9: PANELA DE PRESSÃO ELÉTRICA 5L - 110V | D9: 0 | E9: 394 | F9: 240 | G9: =SUM(D9:F9) | H9: 0 | I9: 146973.66 | J9: 81622.09 | K9: =SUM(H9:J9) | L9: =IF($K$622=0,0,K9/$K$622) | M9: =M8+L9 | N9: =IF(M9<=0.8,"A",IF(M9<=0.95,"B","C"))
A10: 9 | B10: 215517 | C10: KIT AREIA HIGIÊNCIA ESPAÇO DE BICHO - GRÃOS FINOS - 16KG | D10: 0 | E10: 565 | F10: 747 | G10: =SUM(D10:F10) | H10: 0 | I10: 103009.97 | J10: 121977.77 | K10: =SUM(H10:J10) | L10: =IF($K$622=0,0,K10/$K$622) | M10: =M9+L10 | N10: =IF(M10<=0.8,"A",IF(M10<=0.95,"B","C"))
A11: 10 | B11: 213851 | C11: KIT TAPETE HIG ESPACO DE BICHO 50X60 - 200 UNIDADES | D11: 0 | E11: 578 | F11: 519 | G11: =SUM(D11:F11) | H11: 0 | I11: 109305.2 | J11: 95066.1 | K11: =SUM(H11:J11) | L11: =IF($K$622=0,0,K11/$K$622) | M11: =M10+L11 | N11: =IF(M11<=0.8,"A",IF(M11<=0.95,"B","C"))
A12: 11 | B12: 213957 | C12: KIT POTE DE VIDRO MARMITA - 640ML - AZUL - 10 POTES | D12: 1 | E12: 520 | F12: 1108 | G12: =SUM(D12:F12) | H12: 129.9 | I12: 74785.98 | J12: 129103.49 | K12: =SUM(H12:J12) | L12: =IF($K$622=0,0,K12/$K$622) | M12: =M11+L12 | N12: =IF(M12<=0.8,"A",IF(M12<=0.95,"B","C"))
A13: 12 | B13: 215514 | C13: KIT AREIA HIGIÊNCIA ESPAÇO DE BICHO - GRÃOS FINOS - 4KG | D13: 12 | E13: 1977 | F13: 1884 | G13: =SUM(D13:F13) | H13: 518.8 | I13: 108061.66 | J13: 95188.32 | K13: =SUM(H13:J13) | L13: =IF($K$622=0,0,K13/$K$622) | M13: =M12+L13 | N13: =IF(M13<=0.8,"A",IF(M13<=0.95,"B","C"))
A14: 13 | B14: 213860 | C14: CHALEIRA ELETRICA - PRETO - 110V | D14: 1 | E14: 558 | F14: 6113 | G14: =SUM(D14:F14) | H14: 54.9 | I14: 35748.2 | J14: 165423.14 | K14: =SUM(H14:J14) | L14: =IF($K$622=0,0,K14/$K$622) | M14: =M13+L14 | N14: =IF(M14<=0.8,"A",IF(M14<=0.95,"B","C"))
... A621: 620 | B621: 214848 | C621: KIT POTE DE VIDRO C/ TAMPA DE BAMBU - 300ML - 8 UNIDADES | D621: 0 | E621: 0 | F621: 1 | G621: =SUM(D621:F621) | H621: 0 | I621: 0 | J621: 0 | K621: =SUM(H621:J621) | L621: =IF($K$622=0,0,K621/$K$622) | M621: =M620+L621 | N621: =IF(M621<=0.8,"A",IF(M621<=0.95,"B","C"))
C622: TOTAL | D622: =SUM(D2:D621) | E622: =SUM(E2:E621) | F622: =SUM(F2:F621) | G622: =SUM(G2:G621) | H622: =SUM(H2:H621) | I622: =SUM(I2:I621) | J622: =SUM(J2:J621) | K622: =SUM(K2:K621)

Sheet Resumo ABC
A1: Classe | B1: SKUs | C1: % dos SKUs | D1: Qtd Total | E1: Receita Total | F1: % da Receita
A2: A | B2: =COUNTIF('Curva ABC'!$N$2:$N$621,"A") | C2: =IF($B$5=0,0,B2/$B$5) | D2: =SUMIF('Curva ABC'!$N$2:$N$621,"A",'Curva ABC'!$G$2:$G$621) | E2: =SUMIF('Curva ABC'!$N$2:$N$621,"A",'Curva ABC'!$K$2:$K$621) | F2: =IF($E$5=0,0,E2/$E$5)
A3: B | B3: =COUNTIF('Curva ABC'!$N$2:$N$621,"B") | C3: =IF($B$5=0,0,B3/$B$5) | D3: =SUMIF('Curva ABC'!$N$2:$N$621,"B",'Curva ABC'!$G$2:$G$621) | E3: =SUMIF('Curva ABC'!$N$2:$N$621,"B",'Curva ABC'!$K$2:$K$621) | F3: =IF($E$5=0,0,E3/$E$5)
A4: C | B4: =COUNTIF('Curva ABC'!$N$2:$N$621,"C") | C4: =IF($B$5=0,0,B4/$B$5) | D4: =SUMIF('Curva ABC'!$N$2:$N$621,"C",'Curva ABC'!$G$2:$G$621) | E4: =SUMIF('Curva ABC'!$N$2:$N$621,"C",'Curva ABC'!$K$2:$K$621) | F4: =IF($E$5=0,0,E4/$E$5)
A5: TOTAL | B5: =SUM(B2:B4) | D5: =SUM(D2:D4) | E5: =SUM(E2:E4)
